{
"meta":{"test_sets":[],"test_metrics":[],"learn_metrics":[{"best_value":"Min","name":"Logloss"}],"launch_mode":"Train","parameters":"","iteration_count":1000,"learn_sets":["learn"],"name":"experiment"},
"iterations":[
{"learn":[0.6018089363],"iteration":0,"passed_time":0.07569338627,"remaining_time":75.61769288},
{"learn":[0.5020769102],"iteration":1,"passed_time":0.0963139824,"remaining_time":48.06067722},
{"learn":[0.4472481383],"iteration":2,"passed_time":0.1204724742,"remaining_time":40.03701892},
{"learn":[0.4028675204],"iteration":3,"passed_time":0.1457897597,"remaining_time":36.30165018},
{"learn":[0.3674723672],"iteration":4,"passed_time":0.1681566215,"remaining_time":33.46316769},
{"learn":[0.3397843725],"iteration":5,"passed_time":0.1910031649,"remaining_time":31.64285765},
{"learn":[0.3121211224],"iteration":6,"passed_time":0.2188476376,"remaining_time":31.04510059},
{"learn":[0.2917499248],"iteration":7,"passed_time":0.2467954022,"remaining_time":30.60262988},
{"learn":[0.2749038528],"iteration":8,"passed_time":0.2714009449,"remaining_time":29.8842596},
{"learn":[0.2575191049],"iteration":9,"passed_time":0.3032534571,"remaining_time":30.02209225},
{"learn":[0.2473690236],"iteration":10,"passed_time":0.324759028,"remaining_time":29.19878898},
{"learn":[0.2377531368],"iteration":11,"passed_time":0.3498087062,"remaining_time":28.80091681},
{"learn":[0.2279308684],"iteration":12,"passed_time":0.3707448488,"remaining_time":28.14808968},
{"learn":[0.2212512397],"iteration":13,"passed_time":0.3921664137,"remaining_time":27.61972028},
{"learn":[0.210035885],"iteration":14,"passed_time":0.4132287609,"remaining_time":27.1353553},
{"learn":[0.202573299],"iteration":15,"passed_time":0.4358137781,"remaining_time":26.80254735},
{"learn":[0.1942302855],"iteration":16,"passed_time":0.4669878693,"remaining_time":27.0028868},
{"learn":[0.1877938586],"iteration":17,"passed_time":0.4891724123,"remaining_time":26.68707271},
{"learn":[0.183238069],"iteration":18,"passed_time":0.5062796985,"remaining_time":26.14002022},
{"learn":[0.1797364331],"iteration":19,"passed_time":0.5219398049,"remaining_time":25.57505044},
{"learn":[0.1766271032],"iteration":20,"passed_time":0.5434024861,"remaining_time":25.33290638},
{"learn":[0.1724834224],"iteration":21,"passed_time":0.5632489434,"remaining_time":25.03897576},
{"learn":[0.1681076075],"iteration":22,"passed_time":0.5836439903,"remaining_time":24.79218168},
{"learn":[0.1659676461],"iteration":23,"passed_time":0.6065690596,"remaining_time":24.66714176},
{"learn":[0.1636305011],"iteration":24,"passed_time":0.6291899736,"remaining_time":24.53840897},
{"learn":[0.1615296246],"iteration":25,"passed_time":0.6492392879,"remaining_time":24.32150256},
{"learn":[0.1591233614],"iteration":26,"passed_time":0.6677948259,"remaining_time":24.06534687},
{"learn":[0.1572188536],"iteration":27,"passed_time":0.6863781555,"remaining_time":23.8271274},
{"learn":[0.1557160332],"iteration":28,"passed_time":0.7043347202,"remaining_time":23.58306942},
{"learn":[0.1541992553],"iteration":29,"passed_time":0.7226515444,"remaining_time":23.36573327},
{"learn":[0.152711788],"iteration":30,"passed_time":0.7428633508,"remaining_time":23.22047055},
{"learn":[0.1511750456],"iteration":31,"passed_time":0.763000869,"remaining_time":23.08077629},
{"learn":[0.1495155281],"iteration":32,"passed_time":0.7826390492,"remaining_time":22.93369578},
{"learn":[0.1482198841],"iteration":33,"passed_time":0.8014434297,"remaining_time":22.77042215},
{"learn":[0.1447921371],"iteration":34,"passed_time":0.825549474,"remaining_time":22.76157835},
{"learn":[0.1437618651],"iteration":35,"passed_time":0.8490286832,"remaining_time":22.73510141},
{"learn":[0.1428307399],"iteration":36,"passed_time":0.8731290069,"remaining_time":22.72495226},
{"learn":[0.1418335085],"iteration":37,"passed_time":0.895735995,"remaining_time":22.67626387},
{"learn":[0.1405886458],"iteration":38,"passed_time":0.9227786374,"remaining_time":22.73821206},
{"learn":[0.1393059204],"iteration":39,"passed_time":0.9457407155,"remaining_time":22.69777717},
{"learn":[0.1385383668],"iteration":40,"passed_time":0.9668129009,"remaining_time":22.61398956},
{"learn":[0.1375509079],"iteration":41,"passed_time":0.9850734807,"remaining_time":22.46905701},
{"learn":[0.1359835599],"iteration":42,"passed_time":1.005852401,"remaining_time":22.3860639},
{"learn":[0.1347066065],"iteration":43,"passed_time":1.023856073,"remaining_time":22.24560014},
{"learn":[0.1327071614],"iteration":44,"passed_time":1.042899538,"remaining_time":22.13264575},
{"learn":[0.1316579874],"iteration":45,"passed_time":1.061637996,"remaining_time":22.01744887},
{"learn":[0.1304421983],"iteration":46,"passed_time":1.082734376,"remaining_time":21.95416725},
{"learn":[0.1299834785],"iteration":47,"passed_time":1.097076233,"remaining_time":21.75867862},
{"learn":[0.129542077],"iteration":48,"passed_time":1.116111923,"remaining_time":21.66168243},
{"learn":[0.1290790842],"iteration":49,"passed_time":1.134445368,"remaining_time":21.554462},
{"learn":[0.1285283843],"iteration":50,"passed_time":1.150109973,"remaining_time":21.40106597},
{"learn":[0.1280241097],"iteration":51,"passed_time":1.165206622,"remaining_time":21.24261303},
{"learn":[0.1272417589],"iteration":52,"passed_time":1.184441683,"remaining_time":21.1635146},
{"learn":[0.1265525049],"iteration":53,"passed_time":1.204318597,"remaining_time":21.09787764},
{"learn":[0.1258799328],"iteration":54,"passed_time":1.222724737,"remaining_time":21.00863412},
{"learn":[0.1248606979],"iteration":55,"passed_time":1.242665259,"remaining_time":20.9477858},
{"learn":[0.1242196212],"iteration":56,"passed_time":1.260633826,"remaining_time":20.85574909},
{"learn":[0.1240464526],"iteration":57,"passed_time":1.285465259,"remaining_time":20.87772886},
{"learn":[0.1227505088],"iteration":58,"passed_time":1.307185679,"remaining_time":20.8485038},
{"learn":[0.1219310511],"iteration":59,"passed_time":1.330819546,"remaining_time":20.84950622},
{"learn":[0.1214669063],"iteration":60,"passed_time":1.353409182,"remaining_time":20.83362658},
{"learn":[0.1209628767],"iteration":61,"passed_time":1.375707416,"remaining_time":20.81312187},
{"learn":[0.1204269813],"iteration":62,"passed_time":1.390829853,"remaining_time":20.68583448},
{"learn":[0.1197951727],"iteration":63,"passed_time":1.409120459,"remaining_time":20.60838671},
{"learn":[0.1188689244],"iteration":64,"passed_time":1.425072167,"remaining_time":20.49911502},
{"learn":[0.1179641197],"iteration":65,"passed_time":1.44317328,"remaining_time":20.42308854},
{"learn":[0.1175382124],"iteration":66,"passed_time":1.467533046,"remaining_time":20.43594526},
{"learn":[0.117093626],"iteration":67,"passed_time":1.489090894,"remaining_time":20.40930461},
{"learn":[0.1167482248],"iteration":68,"passed_time":1.512160923,"remaining_time":20.40321477},
{"learn":[0.1164256282],"iteration":69,"passed_time":1.532108789,"remaining_time":20.35515962},
{"learn":[0.1161022871],"iteration":70,"passed_time":1.548990846,"remaining_time":20.26778164},
{"learn":[0.1154265977],"iteration":71,"passed_time":1.569477664,"remaining_time":20.22882322},
{"learn":[0.1143861649],"iteration":72,"passed_time":1.588971947,"remaining_time":20.17776705},
{"learn":[0.1141024766],"iteration":73,"passed_time":1.605762143,"remaining_time":20.09372628},
{"learn":[0.11385258],"iteration":74,"passed_time":1.623210123,"remaining_time":20.01959152},
{"learn":[0.1134942866],"iteration":75,"passed_time":1.639581341,"remaining_time":19.93385736},
{"learn":[0.1132629972],"iteration":76,"passed_time":1.6604835,"remaining_time":19.90423728},
{"learn":[0.1129337379],"iteration":77,"passed_time":1.682693581,"remaining_time":19.89030104},
{"learn":[0.112369215],"iteration":78,"passed_time":1.701175362,"remaining_time":19.83268998},
{"learn":[0.1120446175],"iteration":79,"passed_time":1.724119807,"remaining_time":19.82737778},
{"learn":[0.1117097818],"iteration":80,"passed_time":1.741009729,"remaining_time":19.75293754},
{"learn":[0.1108358844],"iteration":81,"passed_time":1.759648612,"remaining_time":19.6994808},
{"learn":[0.110277896],"iteration":82,"passed_time":1.77920512,"remaining_time":19.65700115},
{"learn":[0.1099571829],"iteration":83,"passed_time":1.798259405,"remaining_time":19.60959066},
{"learn":[0.109857665],"iteration":84,"passed_time":1.81529065,"remaining_time":19.54106994},
{"learn":[0.1092686099],"iteration":85,"passed_time":1.831696372,"remaining_time":19.46709866},
{"learn":[0.1090127502],"iteration":86,"passed_time":1.857595509,"remaining_time":19.49407701},
{"learn":[0.1087985181],"iteration":87,"passed_time":1.881214619,"remaining_time":19.49622423},
{"learn":[0.1081520282],"iteration":88,"passed_time":1.903824873,"remaining_time":19.48746583},
{"learn":[0.107969243],"iteration":89,"passed_time":1.924928066,"remaining_time":19.46316156},
{"learn":[0.1077513346],"iteration":90,"passed_time":1.943271179,"remaining_time":19.41135716},
{"learn":[0.1075282743],"iteration":91,"passed_time":1.962505449,"remaining_time":19.36907551},
{"learn":[0.1071405189],"iteration":92,"passed_time":1.980126149,"remaining_time":19.31155287},
{"learn":[0.1070247026],"iteration":93,"passed_time":1.997998447,"remaining_time":19.25730418},
{"learn":[0.1068191603],"iteration":94,"passed_time":2.015338185,"remaining_time":19.19874798},
{"learn":[0.1064461011],"iteration":95,"passed_time":2.034099466,"remaining_time":19.15443663},
{"learn":[0.1059301385],"iteration":96,"passed_time":2.050267185,"remaining_time":19.08650792},
{"learn":[0.1056716031],"iteration":97,"passed_time":2.067564655,"remaining_time":19.03003387},
{"learn":[0.1054189677],"iteration":98,"passed_time":2.087207284,"remaining_time":18.99569457},
{"learn":[0.1051351775],"iteration":99,"passed_time":2.108340953,"remaining_time":18.97506858},
{"learn":[0.1047667949],"iteration":100,"passed_time":2.126955481,"remaining_time":18.93200968},
{"learn":[0.1044767402],"iteration":101,"passed_time":2.144986925,"remaining_time":18.88429665},
{"learn":[0.1041726139],"iteration":102,"passed_time":2.163545749,"remaining_time":18.84175278},
{"learn":[0.1039212061],"iteration":103,"passed_time":2.179176731,"remaining_time":18.77444568},
{"learn":[0.1034242731],"iteration":104,"passed_time":2.196973098,"remaining_time":18.72658022},
{"learn":[0.1032076254],"iteration":105,"passed_time":2.215599237,"remaining_time":18.68628036},
{"learn":[0.1030339761],"iteration":106,"passed_time":2.229375823,"remaining_time":18.60591224},
{"learn":[0.1025609763],"iteration":107,"passed_time":2.24483199,"remaining_time":18.5406494},
{"learn":[0.1022939776],"iteration":108,"passed_time":2.265731986,"remaining_time":18.52079999},
{"learn":[0.1021189906],"iteration":109,"passed_time":2.280736554,"remaining_time":18.45323212},
{"learn":[0.1017958054],"iteration":110,"passed_time":2.301299462,"remaining_time":18.43112813},
{"learn":[0.1015855772],"iteration":111,"passed_time":2.323919675,"remaining_time":18.42536314},
{"learn":[0.1011751366],"iteration":112,"passed_time":2.340413591,"remaining_time":18.37121111},
{"learn":[0.1008758538],"iteration":113,"passed_time":2.359812457,"remaining_time":18.34029681},
{"learn":[0.1006959347],"iteration":114,"passed_time":2.378543381,"remaining_time":18.30444254},
{"learn":[0.1005648949],"iteration":115,"passed_time":2.398519369,"remaining_time":18.27837174},
{"learn":[0.1003042421],"iteration":116,"passed_time":2.41528494,"remaining_time":18.22817608},
{"learn":[0.1000930015],"iteration":117,"passed_time":2.430069278,"remaining_time":18.16373817},
{"learn":[0.09991727086],"iteration":118,"passed_time":2.44920805,"remaining_time":18.1323722},
{"learn":[0.09958893279],"iteration":119,"passed_time":2.468576249,"remaining_time":18.10289249},
{"learn":[0.09921656876],"iteration":120,"passed_time":2.484645205,"remaining_time":18.04961269},
{"learn":[0.09913562386],"iteration":121,"passed_time":2.502821278,"remaining_time":18.01210723},
{"learn":[0.09904903678],"iteration":122,"passed_time":2.522476239,"remaining_time":17.98546066},
{"learn":[0.09889767096],"iteration":123,"passed_time":2.541317368,"remaining_time":17.95317753},
{"learn":[0.09878133251],"iteration":124,"passed_time":2.560553491,"remaining_time":17.92387444},
{"learn":[0.09821761513],"iteration":125,"passed_time":2.575107962,"remaining_time":17.86225682},
{"learn":[0.09799580596],"iteration":126,"passed_time":2.591064189,"remaining_time":17.81101604},
{"learn":[0.0975457529],"iteration":127,"passed_time":2.608615901,"remaining_time":17.77119583},
{"learn":[0.09739658294],"iteration":128,"passed_time":2.625141757,"remaining_time":17.72479434},
{"learn":[0.09714976508],"iteration":129,"passed_time":2.645608527,"remaining_time":17.7052263},
{"learn":[0.09695991149],"iteration":130,"passed_time":2.663050766,"remaining_time":17.66558103},
{"learn":[0.09681706835],"iteration":131,"passed_time":2.683435243,"remaining_time":17.64561963},
{"learn":[0.09666543064],"iteration":132,"passed_time":2.700004709,"remaining_time":17.60078258},
{"learn":[0.09659349168],"iteration":133,"passed_time":2.717256224,"remaining_time":17.5607753},
{"learn":[0.09652896287],"iteration":134,"passed_time":2.7363702,"remaining_time":17.53303869},
{"learn":[0.09632921418],"iteration":135,"passed_time":2.757718007,"remaining_time":17.51962028},
{"learn":[0.09623248338],"iteration":136,"passed_time":2.775731257,"remaining_time":17.48508084},
{"learn":[0.09602704049],"iteration":137,"passed_time":2.795288407,"remaining_time":17.46042469},
{"learn":[0.09577161203],"iteration":138,"passed_time":2.812511949,"remaining_time":17.42138697},
{"learn":[0.09565178432],"iteration":139,"passed_time":2.829784082,"remaining_time":17.38295936},
{"learn":[0.09545658828],"iteration":140,"passed_time":2.850641318,"remaining_time":17.36667299},
{"learn":[0.0952810452],"iteration":141,"passed_time":2.86614859,"remaining_time":17.31799641},
{"learn":[0.09517541371],"iteration":142,"passed_time":2.883360941,"remaining_time":17.28000229},
{"learn":[0.09507359655],"iteration":143,"passed_time":2.902948999,"remaining_time":17.25641905},
{"learn":[0.094830839],"iteration":144,"passed_time":2.921750864,"remaining_time":17.2282551},
{"learn":[0.09478790233],"iteration":145,"passed_time":2.942822549,"remaining_time":17.21349628},
{"learn":[0.09421550546],"iteration":146,"passed_time":2.962233026,"remaining_time":17.18901205},
{"learn":[0.09409611753],"iteration":147,"passed_time":2.982038537,"remaining_time":17.1668705},
{"learn":[0.09391823461],"iteration":148,"passed_time":3.002622926,"remaining_time":17.14920879},
{"learn":[0.09377271585],"iteration":149,"passed_time":3.018313449,"remaining_time":17.10377621},
{"learn":[0.09359270631],"iteration":150,"passed_time":3.034259196,"remaining_time":17.06017257},
{"learn":[0.0935435651],"iteration":151,"passed_time":3.051694302,"remaining_time":17.02524189},
{"learn":[0.09317006157],"iteration":152,"passed_time":3.068302901,"remaining_time":16.98596442},
{"learn":[0.09293981342],"iteration":153,"passed_time":3.083430127,"remaining_time":16.93884342},
{"learn":[0.09282615739],"iteration":154,"passed_time":3.101275695,"remaining_time":16.9069546},
{"learn":[0.09263610073],"iteration":155,"passed_time":3.115136507,"remaining_time":16.85368726},
{"learn":[0.09235132801],"iteration":156,"passed_time":3.137580573,"remaining_time":16.84700906},
{"learn":[0.09225288138],"iteration":157,"passed_time":3.175114184,"remaining_time":16.92054521},
{"learn":[0.09214410089],"iteration":158,"passed_time":3.250868584,"remaining_time":17.19484578},
{"learn":[0.09201081011],"iteration":159,"passed_time":3.28162594,"remaining_time":17.22853619},
{"learn":[0.09180716497],"iteration":160,"passed_time":3.305515703,"remaining_time":17.22563773},
{"learn":[0.09176293586],"iteration":161,"passed_time":3.325069356,"remaining_time":17.20005012},
{"learn":[0.09165625083],"iteration":162,"passed_time":3.345335814,"remaining_time":17.17819678},
{"learn":[0.09153522563],"iteration":163,"passed_time":3.364694825,"remaining_time":17.15173703},
{"learn":[0.09133313793],"iteration":164,"passed_time":3.384617233,"remaining_time":17.12821448},
{"learn":[0.09112343883],"iteration":165,"passed_time":3.405108569,"remaining_time":17.10759365},
{"learn":[0.09093594242],"iteration":166,"passed_time":3.42712493,"remaining_time":17.09458124},
{"learn":[0.09073726437],"iteration":167,"passed_time":3.445303918,"remaining_time":17.0624575},
{"learn":[0.09054803815],"iteration":168,"passed_time":3.458843332,"remaining_time":17.00768526},
{"learn":[0.09034700049],"iteration":169,"passed_time":3.475576974,"remaining_time":16.96899346},
{"learn":[0.09030897569],"iteration":170,"passed_time":3.495334706,"remaining_time":16.94521913},
{"learn":[0.0901972407],"iteration":171,"passed_time":3.508432661,"remaining_time":16.88943165},
{"learn":[0.09003021173],"iteration":172,"passed_time":3.526152005,"remaining_time":16.85622952},
{"learn":[0.08989351283],"iteration":173,"passed_time":3.545524551,"remaining_time":16.83105333},
{"learn":[0.08972229661],"iteration":174,"passed_time":3.569110388,"remaining_time":16.82580612},
{"learn":[0.08968369016],"iteration":175,"passed_time":3.588182276,"remaining_time":16.79921702},
{"learn":[0.0892261177],"iteration":176,"passed_time":3.608094706,"remaining_time":16.77662115},
{"learn":[0.08908838306],"iteration":177,"passed_time":3.625895221,"remaining_time":16.74430265},
{"learn":[0.08896826493],"iteration":178,"passed_time":3.646959451,"remaining_time":16.7271157},
{"learn":[0.08887339012],"iteration":179,"passed_time":3.686454017,"remaining_time":16.79384608},
{"learn":[0.08877971053],"iteration":180,"passed_time":3.722500525,"remaining_time":16.84380072},
{"learn":[0.08868896264],"iteration":181,"passed_time":3.757253277,"remaining_time":16.8869955},
{"learn":[0.08861683394],"iteration":182,"passed_time":3.779595804,"remaining_time":16.87393318},
{"learn":[0.08853351018],"iteration":183,"passed_time":3.802941004,"remaining_time":16.86521663},
{"learn":[0.08846266577],"iteration":184,"passed_time":3.822290778,"remaining_time":16.83874045},
{"learn":[0.08836846479],"iteration":185,"passed_time":3.839486549,"remaining_time":16.80291425},
{"learn":[0.08826905755],"iteration":186,"passed_time":3.855546578,"remaining_time":16.76234956},
{"learn":[0.08808973679],"iteration":187,"passed_time":3.872160147,"remaining_time":16.72443638},
{"learn":[0.08803034048],"iteration":188,"passed_time":3.891760867,"remaining_time":16.69956647},
{"learn":[0.08792321731],"iteration":189,"passed_time":3.904721977,"remaining_time":16.64644632},
{"learn":[0.08764404989],"iteration":190,"passed_time":3.92562576,"remaining_time":16.62738869},
{"learn":[0.08752531233],"iteration":191,"passed_time":3.943083377,"remaining_time":16.59380921},
{"learn":[0.08747905826],"iteration":192,"passed_time":3.958562056,"remaining_time":16.55212217},
{"learn":[0.08729065177],"iteration":193,"passed_time":3.97826132,"remaining_time":16.52824033},
{"learn":[0.08725209767],"iteration":194,"passed_time":3.998396494,"remaining_time":16.50620091},
{"learn":[0.08703274729],"iteration":195,"passed_time":4.019090527,"remaining_time":16.48647338},
{"learn":[0.08688999886],"iteration":196,"passed_time":4.044640595,"remaining_time":16.48652994},
{"learn":[0.08681301371],"iteration":197,"passed_time":4.064004565,"remaining_time":16.46127102},
{"learn":[0.08673430823],"iteration":198,"passed_time":4.085301028,"remaining_time":16.44384987},
{"learn":[0.0866016956],"iteration":199,"passed_time":4.101037817,"remaining_time":16.40415127},
{"learn":[0.08652599794],"iteration":200,"passed_time":4.122559988,"remaining_time":16.38768871},
{"learn":[0.08642782885],"iteration":201,"passed_time":4.140910555,"remaining_time":16.35864665},
{"learn":[0.08631277066],"iteration":202,"passed_time":4.157750324,"remaining_time":16.32377837},
{"learn":[0.0862005328],"iteration":203,"passed_time":4.179165557,"remaining_time":16.30694012},
{"learn":[0.08612854738],"iteration":204,"passed_time":4.199346216,"remaining_time":16.28526947},
{"learn":[0.08605009449],"iteration":205,"passed_time":4.219815892,"remaining_time":16.26472727},
{"learn":[0.08587237978],"iteration":206,"passed_time":4.242657977,"remaining_time":16.25327428},
{"learn":[0.0857588266],"iteration":207,"passed_time":4.260109743,"remaining_time":16.2211871},
{"learn":[0.08569175844],"iteration":208,"passed_time":4.279873216,"remaining_time":16.19798906},
{"learn":[0.0855529113],"iteration":209,"passed_time":4.296853987,"remaining_time":16.16435548},
{"learn":[0.08549037213],"iteration":210,"passed_time":4.319091008,"remaining_time":16.15053462},
{"learn":[0.08542002408],"iteration":211,"passed_time":4.339589637,"remaining_time":16.1301728},
{"learn":[0.08537533154],"iteration":212,"passed_time":4.358279394,"remaining_time":16.10312621},
{"learn":[0.08532437262],"iteration":213,"passed_time":4.377320475,"remaining_time":16.0774481},
{"learn":[0.08526986693],"iteration":214,"passed_time":4.397656091,"remaining_time":16.05655829},
{"learn":[0.08525313912],"iteration":215,"passed_time":4.418610177,"remaining_time":16.03791842},
{"learn":[0.0852272277],"iteration":216,"passed_time":4.438208584,"remaining_time":16.01436553},
{"learn":[0.08513391613],"iteration":217,"passed_time":4.458100626,"remaining_time":15.99190224},
{"learn":[0.08507929929],"iteration":218,"passed_time":4.479158935,"remaining_time":15.97362159},
{"learn":[0.0850412601],"iteration":219,"passed_time":4.495928444,"remaining_time":15.94010994},
{"learn":[0.08493524254],"iteration":220,"passed_time":4.518634997,"remaining_time":15.92767721},
{"learn":[0.08482619796],"iteration":221,"passed_time":4.537660308,"remaining_time":15.90225099},
{"learn":[0.08465018492],"iteration":222,"passed_time":4.556555076,"remaining_time":15.87642733},
{"learn":[0.0846197281],"iteration":223,"passed_time":4.57574846,"remaining_time":15.85170002},
{"learn":[0.08432162967],"iteration":224,"passed_time":4.596449145,"remaining_time":15.83221372},
{"learn":[0.08419280429],"iteration":225,"passed_time":4.618696655,"remaining_time":15.81801421},
{"learn":[0.08413182943],"iteration":226,"passed_time":4.638187862,"remaining_time":15.79435778},
{"learn":[0.08408575871],"iteration":227,"passed_time":4.657659042,"remaining_time":15.77067009},
{"learn":[0.0839087126],"iteration":228,"passed_time":4.681360804,"remaining_time":15.7612628},
{"learn":[0.08385258333],"iteration":229,"passed_time":4.696829355,"remaining_time":15.72416784},
{"learn":[0.08377516418],"iteration":230,"passed_time":4.716382717,"remaining_time":15.70085848},
{"learn":[0.08366853683],"iteration":231,"passed_time":4.735005019,"remaining_time":15.67449937},
{"learn":[0.08360827047],"iteration":232,"passed_time":4.751990189,"remaining_time":15.64281749},
{"learn":[0.08351181514],"iteration":233,"passed_time":4.773156299,"remaining_time":15.62494754},
{"learn":[0.08344187751],"iteration":234,"passed_time":4.795112918,"remaining_time":15.6096229},
{"learn":[0.08337284259],"iteration":235,"passed_time":4.871257353,"remaining_time":15.76966363},
{"learn":[0.08321252257],"iteration":236,"passed_time":4.89300294,"remaining_time":15.75257908},
{"learn":[0.08313100405],"iteration":237,"passed_time":4.919532068,"remaining_time":15.75077074},
{"learn":[0.08309544824],"iteration":238,"passed_time":4.948203998,"remaining_time":15.75557842},
{"learn":[0.08303304417],"iteration":239,"passed_time":4.989481688,"remaining_time":15.80002535},
{"learn":[0.08296942555],"iteration":240,"passed_time":5.016974618,"remaining_time":15.80034745},
{"learn":[0.08290211029],"iteration":241,"passed_time":5.051020236,"remaining_time":15.82096421},
{"learn":[0.08282679271],"iteration":242,"passed_time":5.084272329,"remaining_time":15.83865907},
{"learn":[0.08278281624],"iteration":243,"passed_time":5.100340434,"remaining_time":15.80269413},
{"learn":[0.08273866857],"iteration":244,"passed_time":5.116481925,"remaining_time":15.76711777},
{"learn":[0.08265969446],"iteration":245,"passed_time":5.13128025,"remaining_time":15.72758255},
{"learn":[0.08258626374],"iteration":246,"passed_time":5.149475829,"remaining_time":15.69860445},
{"learn":[0.08251068329],"iteration":247,"passed_time":5.17460223,"remaining_time":15.69072934},
{"learn":[0.08247414027],"iteration":248,"passed_time":5.197826435,"remaining_time":15.67697852},
{"learn":[0.08243062915],"iteration":249,"passed_time":5.22928801,"remaining_time":15.68786403},
{"learn":[0.08240524028],"iteration":250,"passed_time":5.25276725,"remaining_time":15.67459231},
{"learn":[0.08234855827],"iteration":251,"passed_time":5.272406602,"remaining_time":15.64984182},
{"learn":[0.08223698497],"iteration":252,"passed_time":5.29171003,"remaining_time":15.62413989},
{"learn":[0.08219478987],"iteration":253,"passed_time":5.309006317,"remaining_time":15.59259336},
{"learn":[0.08211693443],"iteration":254,"passed_time":5.325467192,"remaining_time":15.55871788},
{"learn":[0.08203259933],"iteration":255,"passed_time":5.34374263,"remaining_time":15.53025202},
{"learn":[0.08197578431],"iteration":256,"passed_time":5.361761199,"remaining_time":15.50112285},
{"learn":[0.08185485105],"iteration":257,"passed_time":5.381153423,"remaining_time":15.47603039},
{"learn":[0.08179091075],"iteration":258,"passed_time":5.401360019,"remaining_time":15.45331187},
{"learn":[0.0817124783],"iteration":259,"passed_time":5.422271025,"remaining_time":15.43261753},
{"learn":[0.08164500025],"iteration":260,"passed_time":5.445580729,"remaining_time":15.41871325},
{"learn":[0.08154315588],"iteration":261,"passed_time":5.465982168,"remaining_time":15.39654519},
{"learn":[0.08149521948],"iteration":262,"passed_time":5.484075918,"remaining_time":15.36792377},
{"learn":[0.08143957107],"iteration":263,"passed_time":5.502228407,"remaining_time":15.33954586},
{"learn":[0.08141239855],"iteration":264,"passed_time":5.518354749,"remaining_time":15.30562544},
{"learn":[0.08140461338],"iteration":265,"passed_time":5.533281783,"remaining_time":15.26852943},
{"learn":[0.08129988257],"iteration":266,"passed_time":5.549725987,"remaining_time":15.2357646},
{"learn":[0.08123284737],"iteration":267,"passed_time":5.565185701,"remaining_time":15.20043259},
{"learn":[0.08120063728],"iteration":268,"passed_time":5.583331377,"remaining_time":15.17254735},
{"learn":[0.08109437181],"iteration":269,"passed_time":5.598427786,"remaining_time":15.13648994},
{"learn":[0.08105184053],"iteration":270,"passed_time":5.620362254,"remaining_time":15.11898186},
{"learn":[0.0809827652],"iteration":271,"passed_time":5.639297808,"remaining_time":15.09341472},
{"learn":[0.08096085977],"iteration":272,"passed_time":5.657931792,"remaining_time":15.06709309},
{"learn":[0.08085352369],"iteration":273,"passed_time":5.680003335,"remaining_time":15.04993584},
{"learn":[0.0807957163],"iteration":274,"passed_time":5.698738407,"remaining_time":15.02394671},
{"learn":[0.08075702825],"iteration":275,"passed_time":5.716444896,"remaining_time":14.99531197},
{"learn":[0.08064111312],"iteration":276,"passed_time":5.733279125,"remaining_time":14.96447945},
{"learn":[0.08056627499],"iteration":277,"passed_time":5.753484069,"remaining_time":14.94250179},
{"learn":[0.08043940184],"iteration":278,"passed_time":5.770833435,"remaining_time":14.91315737},
{"learn":[0.08038098266],"iteration":279,"passed_time":5.786193243,"remaining_time":14.87878263},
{"learn":[0.08029570233],"iteration":280,"passed_time":5.803979291,"remaining_time":14.85075128},
{"learn":[0.08026693943],"iteration":281,"passed_time":5.819188088,"remaining_time":14.81623066},
{"learn":[0.08024609629],"iteration":282,"passed_time":5.837289542,"remaining_time":14.78917527},
{"learn":[0.08018625461],"iteration":283,"passed_time":5.859040089,"remaining_time":14.77138276},
{"learn":[0.08015047823],"iteration":284,"passed_time":5.879865385,"remaining_time":14.75124123},
{"learn":[0.08012265347],"iteration":285,"passed_time":5.897233286,"remaining_time":14.72246352},
{"learn":[0.08010638915],"iteration":286,"passed_time":5.912584899,"remaining_time":14.68875621},
{"learn":[0.08007723196],"iteration":287,"passed_time":5.927645852,"remaining_time":14.6544578},
{"learn":[0.07990601418],"iteration":288,"passed_time":5.945152059,"remaining_time":14.62630835},
{"learn":[0.0797596467],"iteration":289,"passed_time":5.963134171,"remaining_time":14.59939745},
{"learn":[0.07974141983],"iteration":290,"passed_time":5.981715477,"remaining_time":14.57400781},
{"learn":[0.07971159245],"iteration":291,"passed_time":5.997613786,"remaining_time":14.54215945},
{"learn":[0.07967779607],"iteration":292,"passed_time":6.013875561,"remaining_time":14.511297},
{"learn":[0.07963885191],"iteration":293,"passed_time":6.031024665,"remaining_time":14.48266467},
{"learn":[0.07953632322],"iteration":294,"passed_time":6.050504982,"remaining_time":14.4596814},
{"learn":[0.07949074176],"iteration":295,"passed_time":6.07052429,"remaining_time":14.43800372},
{"learn":[0.07945983658],"iteration":296,"passed_time":6.086992228,"remaining_time":14.4079311},
{"learn":[0.07939288604],"iteration":297,"passed_time":6.104864777,"remaining_time":14.38125864},
{"learn":[0.07931285675],"iteration":298,"passed_time":6.120630379,"remaining_time":14.34970534},
{"learn":[0.07923518455],"iteration":299,"passed_time":6.134460945,"remaining_time":14.31374221},
{"learn":[0.07905178037],"iteration":300,"passed_time":6.151257474,"remaining_time":14.28481387},
{"learn":[0.07895890032],"iteration":301,"passed_time":6.16940872,"remaining_time":14.25909698},
{"learn":[0.07888364634],"iteration":302,"passed_time":6.189120638,"remaining_time":14.23702008},
{"learn":[0.07883760244],"iteration":303,"passed_time":6.208803481,"remaining_time":14.21489218},
{"learn":[0.0787730455],"iteration":304,"passed_time":6.226335005,"remaining_time":14.18787813},
{"learn":[0.07872222603],"iteration":305,"passed_time":6.247138391,"remaining_time":14.16834655},
{"learn":[0.07868555815],"iteration":306,"passed_time":6.268962354,"remaining_time":14.15111046},
{"learn":[0.07863155396],"iteration":307,"passed_time":6.288725867,"remaining_time":14.12921526},
{"learn":[0.07855812845],"iteration":308,"passed_time":6.30733223,"remaining_time":14.10474618},
{"learn":[0.07852041028],"iteration":309,"passed_time":6.324806788,"remaining_time":14.07779575},
{"learn":[0.07848432541],"iteration":310,"passed_time":6.342426056,"remaining_time":14.05122686},
{"learn":[0.07844968684],"iteration":311,"passed_time":6.359535867,"remaining_time":14.02359191},
{"learn":[0.07843289278],"iteration":312,"passed_time":6.375485832,"remaining_time":13.99347849},
{"learn":[0.07839416717],"iteration":313,"passed_time":6.394699032,"remaining_time":13.97058451},
{"learn":[0.07837216718],"iteration":314,"passed_time":6.408394167,"remaining_time":13.9357143},
{"learn":[0.07828693192],"iteration":315,"passed_time":6.423561327,"remaining_time":13.90416439},
{"learn":[0.07823721808],"iteration":316,"passed_time":6.443621742,"remaining_time":13.88326072},
{"learn":[0.07821021302],"iteration":317,"passed_time":6.46302749,"remaining_time":13.86095833},
{"learn":[0.07816629739],"iteration":318,"passed_time":6.483891949,"remaining_time":13.84178814},
{"learn":[0.07814210347],"iteration":319,"passed_time":6.502799752,"remaining_time":13.81844947},
{"learn":[0.07810304705],"iteration":320,"passed_time":6.519526812,"remaining_time":13.79052556},
{"learn":[0.07806210754],"iteration":321,"passed_time":6.535760594,"remaining_time":13.76163256},
{"learn":[0.07799840127],"iteration":322,"passed_time":6.552295707,"remaining_time":13.73344952},
{"learn":[0.07797089842],"iteration":323,"passed_time":6.569547231,"remaining_time":13.70683311},
{"learn":[0.07787947299],"iteration":324,"passed_time":6.589591175,"remaining_time":13.68607398},
{"learn":[0.07779158128],"iteration":325,"passed_time":6.605494975,"remaining_time":13.65675955},
{"learn":[0.07773464084],"iteration":326,"passed_time":6.621012095,"remaining_time":13.62673132},
{"learn":[0.07768566933],"iteration":327,"passed_time":6.637973901,"remaining_time":13.59975141},
{"learn":[0.07761985349],"iteration":328,"passed_time":6.655619678,"remaining_time":13.57422737},
{"learn":[0.07756041043],"iteration":329,"passed_time":6.675943192,"remaining_time":13.55418769},
{"learn":[0.07749006174],"iteration":330,"passed_time":6.700106052,"remaining_time":13.54190619},
{"learn":[0.07745224405],"iteration":331,"passed_time":6.718576131,"remaining_time":13.51809896},
{"learn":[0.0774075155],"iteration":332,"passed_time":6.735124789,"remaining_time":13.49047518},
{"learn":[0.07737553963],"iteration":333,"passed_time":6.753900216,"remaining_time":13.46735792},
{"learn":[0.07730018701],"iteration":334,"passed_time":6.772342644,"remaining_time":13.44360555},
{"learn":[0.07727290788],"iteration":335,"passed_time":6.790142948,"remaining_time":13.41861583},
{"learn":[0.07718264675],"iteration":336,"passed_time":6.805402961,"remaining_time":13.38867111},
{"learn":[0.07705715645],"iteration":337,"passed_time":6.822612597,"remaining_time":13.36263177},
{"learn":[0.07693744031],"iteration":338,"passed_time":6.844158934,"remaining_time":13.34510046},
{"learn":[0.07685700564],"iteration":339,"passed_time":6.865166629,"remaining_time":13.32649993},
{"learn":[0.07675731149],"iteration":340,"passed_time":6.886914561,"remaining_time":13.30931582},
{"learn":[0.07669222724],"iteration":341,"passed_time":6.907471849,"remaining_time":13.28981426},
{"learn":[0.07659423608],"iteration":342,"passed_time":6.928630225,"remaining_time":13.27145789},
{"learn":[0.07656167991],"iteration":343,"passed_time":6.947411873,"remaining_time":13.24855287},
{"learn":[0.07654744913],"iteration":344,"passed_time":6.965349082,"remaining_time":13.22406855},
{"learn":[0.07651185147],"iteration":345,"passed_time":6.985095383,"remaining_time":13.20304156},
{"learn":[0.07648839866],"iteration":346,"passed_time":7.000603457,"remaining_time":13.17404627},
{"learn":[0.07645016438],"iteration":347,"passed_time":7.016708921,"remaining_time":13.14624775},
{"learn":[0.07640710426],"iteration":348,"passed_time":7.034401966,"remaining_time":13.12147759},
{"learn":[0.07635725275],"iteration":349,"passed_time":7.053033906,"remaining_time":13.09849154},
{"learn":[0.07631686091],"iteration":350,"passed_time":7.071633716,"remaining_time":13.07547089},
{"learn":[0.07628897212],"iteration":351,"passed_time":7.091339792,"remaining_time":13.05451189},
{"learn":[0.07618012327],"iteration":352,"passed_time":7.111386251,"remaining_time":13.03418387},
{"learn":[0.07611800692],"iteration":353,"passed_time":7.132794381,"remaining_time":13.01634229},
{"learn":[0.0761163804],"iteration":354,"passed_time":7.149118362,"remaining_time":12.98924322},
{"learn":[0.07604021359],"iteration":355,"passed_time":7.16760948,"remaining_time":12.96612501},
{"learn":[0.07601367312],"iteration":356,"passed_time":7.187042138,"remaining_time":12.94472856},
{"learn":[0.07598661348],"iteration":357,"passed_time":7.202804124,"remaining_time":12.91676047},
{"learn":[0.07595675855],"iteration":358,"passed_time":7.220171113,"remaining_time":12.89172614},
{"learn":[0.07589409998],"iteration":359,"passed_time":7.239548308,"remaining_time":12.8703081},
{"learn":[0.07585512539],"iteration":360,"passed_time":7.257920475,"remaining_time":12.84712239},
{"learn":[0.07580368236],"iteration":361,"passed_time":7.278468736,"remaining_time":12.82779849},
{"learn":[0.07574463467],"iteration":362,"passed_time":7.296001584,"remaining_time":12.80317633},
{"learn":[0.07570726483],"iteration":363,"passed_time":7.317041439,"remaining_time":12.78472076},
{"learn":[0.07566617027],"iteration":364,"passed_time":7.337138262,"remaining_time":12.7646104},
{"learn":[0.07562481158],"iteration":365,"passed_time":7.358704906,"remaining_time":12.7470462},
{"learn":[0.07557692257],"iteration":366,"passed_time":7.379118618,"remaining_time":12.72747162},
{"learn":[0.07552152666],"iteration":367,"passed_time":7.397177763,"remaining_time":12.70384877},
{"learn":[0.07544875874],"iteration":368,"passed_time":7.414502994,"remaining_time":12.67900106},
{"learn":[0.07541090351],"iteration":369,"passed_time":7.434559472,"remaining_time":12.65884451},
{"learn":[0.07537244317],"iteration":370,"passed_time":7.452965422,"remaining_time":12.63589016},
{"learn":[0.07531500857],"iteration":371,"passed_time":7.471337008,"remaining_time":12.61290226},
{"learn":[0.07526717252],"iteration":372,"passed_time":7.489215808,"remaining_time":12.58911076},
{"learn":[0.07518635974],"iteration":373,"passed_time":7.510395253,"remaining_time":12.57087548},
{"learn":[0.07514938985],"iteration":374,"passed_time":7.534368731,"remaining_time":12.55728122},
{"learn":[0.07510941814],"iteration":375,"passed_time":7.555334879,"remaining_time":12.53864086},
{"learn":[0.07505424603],"iteration":376,"passed_time":7.579324778,"remaining_time":12.52498498},
{"learn":[0.07502674819],"iteration":377,"passed_time":7.593996878,"remaining_time":12.49594195},
{"learn":[0.07499814945],"iteration":378,"passed_time":7.610439198,"remaining_time":12.46987531},
{"learn":[0.0748583996],"iteration":379,"passed_time":7.629566929,"remaining_time":12.44824078},
{"learn":[0.07479833429],"iteration":380,"passed_time":7.644353182,"remaining_time":12.41956593},
{"learn":[0.07477084242],"iteration":381,"passed_time":7.662781463,"remaining_time":12.39685587},
{"learn":[0.0747134865],"iteration":382,"passed_time":7.682165391,"remaining_time":12.37570769},
{"learn":[0.07467550502],"iteration":383,"passed_time":7.700260052,"remaining_time":12.3525005},
{"learn":[0.07464974873],"iteration":384,"passed_time":7.71985942,"remaining_time":12.33172349},
{"learn":[0.07461278331],"iteration":385,"passed_time":7.740575273,"remaining_time":12.31272854},
{"learn":[0.07456967697],"iteration":386,"passed_time":7.764658816,"remaining_time":12.29905905},
{"learn":[0.07452675997],"iteration":387,"passed_time":7.783569935,"remaining_time":12.27717732},
{"learn":[0.0744956936],"iteration":388,"passed_time":7.803776581,"remaining_time":12.25734574},
{"learn":[0.0744476814],"iteration":389,"passed_time":7.821230211,"remaining_time":12.23320623},
{"learn":[0.07443155234],"iteration":390,"passed_time":7.836825257,"remaining_time":12.20620609},
{"learn":[0.07437482785],"iteration":391,"passed_time":7.854986121,"remaining_time":12.18324378},
{"learn":[0.07431760692],"iteration":392,"passed_time":7.874367794,"remaining_time":12.16219148},
{"learn":[0.07425258873],"iteration":393,"passed_time":7.894765306,"remaining_time":12.14271009},
{"learn":[0.07417424337],"iteration":394,"passed_time":7.912147874,"remaining_time":12.11860624},
{"learn":[0.07403947902],"iteration":395,"passed_time":7.933562716,"remaining_time":12.10068657},
{"learn":[0.07396029847],"iteration":396,"passed_time":7.953979063,"remaining_time":12.08123268},
{"learn":[0.07391782242],"iteration":397,"passed_time":7.975733827,"remaining_time":12.0637984},
{"learn":[0.07387582012],"iteration":398,"passed_time":7.992289778,"remaining_time":12.03851167},
{"learn":[0.07385903879],"iteration":399,"passed_time":8.013093855,"remaining_time":12.01964078},
{"learn":[0.07382035943],"iteration":400,"passed_time":8.031743338,"remaining_time":11.99754179},
{"learn":[0.0737839421],"iteration":401,"passed_time":8.050889143,"remaining_time":11.97619828},
{"learn":[0.07376010824],"iteration":402,"passed_time":8.068969949,"remaining_time":11.95328799},
{"learn":[0.07372312081],"iteration":403,"passed_time":8.093123211,"remaining_time":11.93935998},
{"learn":[0.07367498028],"iteration":404,"passed_time":8.109964893,"remaining_time":11.91463978},
{"learn":[0.07365965856],"iteration":405,"passed_time":8.128763172,"remaining_time":11.892821},
{"learn":[0.07362079407],"iteration":406,"passed_time":8.14856123,"remaining_time":11.87247373},
{"learn":[0.07358946423],"iteration":407,"passed_time":8.171112975,"remaining_time":11.85612471},
{"learn":[0.07353000802],"iteration":408,"passed_time":8.197017041,"remaining_time":11.84458942},
{"learn":[0.07349201211],"iteration":409,"passed_time":8.21688562,"remaining_time":11.82429882},
{"learn":[0.07346400411],"iteration":410,"passed_time":8.235820683,"remaining_time":11.80267246},
{"learn":[0.07340506115],"iteration":411,"passed_time":8.257429145,"remaining_time":11.78487461},
{"learn":[0.07328298885],"iteration":412,"passed_time":8.278464422,"remaining_time":11.76624362},
{"learn":[0.07323644549],"iteration":413,"passed_time":8.298633679,"remaining_time":11.74637521},
{"learn":[0.07316410499],"iteration":414,"passed_time":8.317436557,"remaining_time":11.72457924},
{"learn":[0.07311308956],"iteration":415,"passed_time":8.334740759,"remaining_time":11.70069376},
{"learn":[0.07307042552],"iteration":416,"passed_time":8.359415951,"remaining_time":11.68714508},
{"learn":[0.0730304033],"iteration":417,"passed_time":8.380945437,"remaining_time":11.66916326},
{"learn":[0.07299036181],"iteration":418,"passed_time":8.405701549,"remaining_time":11.65563866},
{"learn":[0.07296431186],"iteration":419,"passed_time":8.424537789,"remaining_time":11.63388552},
{"learn":[0.07293326699],"iteration":420,"passed_time":8.446637925,"remaining_time":11.61663506},
{"learn":[0.07289119133],"iteration":421,"passed_time":8.471554446,"remaining_time":11.60321912},
{"learn":[0.07284839535],"iteration":422,"passed_time":8.492863832,"remaining_time":11.58482844},
{"learn":[0.07280567517],"iteration":423,"passed_time":8.512839199,"remaining_time":11.56461174},
{"learn":[0.07279147222],"iteration":424,"passed_time":8.528982143,"remaining_time":11.53921113},
{"learn":[0.07278541991],"iteration":425,"passed_time":8.546449829,"remaining_time":11.51563897},
{"learn":[0.07275479098],"iteration":426,"passed_time":8.566129506,"remaining_time":11.49506372},
{"learn":[0.07272265121],"iteration":427,"passed_time":8.587567031,"remaining_time":11.47684192},
{"learn":[0.07271301147],"iteration":428,"passed_time":8.609813579,"remaining_time":11.45968194},
{"learn":[0.07267973],"iteration":429,"passed_time":8.62996892,"remaining_time":11.43972624},
{"learn":[0.0726443718],"iteration":430,"passed_time":8.649205524,"remaining_time":11.41855671},
{"learn":[0.07261370585],"iteration":431,"passed_time":8.669281478,"remaining_time":11.39849972},
{"learn":[0.07259884346],"iteration":432,"passed_time":8.689743078,"remaining_time":11.37894763},
{"learn":[0.07258689395],"iteration":433,"passed_time":8.708406477,"remaining_time":11.35704623},
{"learn":[0.07256950623],"iteration":434,"passed_time":8.724884483,"remaining_time":11.33232123},
{"learn":[0.07255967374],"iteration":435,"passed_time":8.741489155,"remaining_time":11.3077979},
{"learn":[0.072516355],"iteration":436,"passed_time":8.760012854,"remaining_time":11.28578315},
{"learn":[0.07249198147],"iteration":437,"passed_time":8.776110113,"remaining_time":11.26067097},
{"learn":[0.07245411092],"iteration":438,"passed_time":8.796277427,"remaining_time":11.24080099},
{"learn":[0.07244873039],"iteration":439,"passed_time":8.817358919,"remaining_time":11.22209317},
{"learn":[0.07239113243],"iteration":440,"passed_time":8.834406064,"remaining_time":11.19826075},
{"learn":[0.07226395502],"iteration":441,"passed_time":8.852867116,"remaining_time":11.17624401},
{"learn":[0.07224473681],"iteration":442,"passed_time":8.868567447,"remaining_time":11.15077216},
{"learn":[0.07218842745],"iteration":443,"passed_time":8.885772666,"remaining_time":11.12722883},
{"learn":[0.07215181466],"iteration":444,"passed_time":8.902702812,"remaining_time":11.10337092},
{"learn":[0.072129479],"iteration":445,"passed_time":8.918550287,"remaining_time":11.07819924},
{"learn":[0.07208703703],"iteration":446,"passed_time":8.938536685,"remaining_time":11.05818968},
{"learn":[0.07202874898],"iteration":447,"passed_time":8.959354678,"remaining_time":11.03920487},
{"learn":[0.07201254143],"iteration":448,"passed_time":8.979086842,"remaining_time":11.0188794},
{"learn":[0.07197415003],"iteration":449,"passed_time":9.004886424,"remaining_time":11.0059723},
{"learn":[0.07194655164],"iteration":450,"passed_time":9.022580882,"remaining_time":10.98314169},
{"learn":[0.07191142984],"iteration":451,"passed_time":9.040464251,"remaining_time":10.96056285},
{"learn":[0.07186111993],"iteration":452,"passed_time":9.058250328,"remaining_time":10.93788726},
{"learn":[0.07177456397],"iteration":453,"passed_time":9.075778928,"remaining_time":10.91492356},
{"learn":[0.07172048609],"iteration":454,"passed_time":9.092342533,"remaining_time":10.89082787},
{"learn":[0.07166233578],"iteration":455,"passed_time":9.110668585,"remaining_time":10.86886779},
{"learn":[0.07164159788],"iteration":456,"passed_time":9.125048061,"remaining_time":10.84223435},
{"learn":[0.07161287096],"iteration":457,"passed_time":9.140010501,"remaining_time":10.8163443},
{"learn":[0.0715708754],"iteration":458,"passed_time":9.161112992,"remaining_time":10.79773884},
{"learn":[0.07153500095],"iteration":459,"passed_time":9.177997054,"remaining_time":10.77417045},
{"learn":[0.07148308047],"iteration":460,"passed_time":9.199787704,"remaining_time":10.75636784},
{"learn":[0.07146437449],"iteration":461,"passed_time":9.215531667,"remaining_time":10.73150657},
{"learn":[0.07144409306],"iteration":462,"passed_time":9.234377675,"remaining_time":10.71028253},
{"learn":[0.07140618532],"iteration":463,"passed_time":9.254101744,"remaining_time":10.69008305},
{"learn":[0.07139209033],"iteration":464,"passed_time":9.268247206,"remaining_time":10.66346722},
{"learn":[0.07138024606],"iteration":465,"passed_time":9.284276648,"remaining_time":10.6390638},
{"learn":[0.071322949],"iteration":466,"passed_time":9.301907848,"remaining_time":10.61652438},
{"learn":[0.07128635481],"iteration":467,"passed_time":9.316879345,"remaining_time":10.5909825},
{"learn":[0.07121519662],"iteration":468,"passed_time":9.333823859,"remaining_time":10.56771955},
{"learn":[0.07118418288],"iteration":469,"passed_time":9.356282661,"remaining_time":10.55070172},
{"learn":[0.07115245396],"iteration":470,"passed_time":9.377357101,"remaining_time":10.53210596},
{"learn":[0.07110186354],"iteration":471,"passed_time":9.398724164,"remaining_time":10.51382703},
{"learn":[0.07107771247],"iteration":472,"passed_time":9.418022854,"remaining_time":10.49323054},
{"learn":[0.07105208138],"iteration":473,"passed_time":9.436409928,"remaining_time":10.4716279},
{"learn":[0.0710283618],"iteration":474,"passed_time":9.454050746,"remaining_time":10.44921398},
{"learn":[0.07098261729],"iteration":475,"passed_time":9.468609746,"remaining_time":10.42342754},
{"learn":[0.07087671319],"iteration":476,"passed_time":9.484643106,"remaining_time":10.39930471},
{"learn":[0.07085444344],"iteration":477,"passed_time":9.499934858,"remaining_time":10.37440585},
{"learn":[0.07081816339],"iteration":478,"passed_time":9.516255131,"remaining_time":10.35066581},
{"learn":[0.07079014994],"iteration":479,"passed_time":9.532648911,"remaining_time":10.32703632},
{"learn":[0.07075338075],"iteration":480,"passed_time":9.552953831,"remaining_time":10.30765704},
{"learn":[0.07072493067],"iteration":481,"passed_time":9.569486609,"remaining_time":10.28422005},
{"learn":[0.07070275368],"iteration":482,"passed_time":9.589145728,"remaining_time":10.26415806},
{"learn":[0.07066299646],"iteration":483,"passed_time":9.609504889,"remaining_time":10.24484405},
{"learn":[0.07064308013],"iteration":484,"passed_time":9.628182684,"remaining_time":10.22374038},
{"learn":[0.07060358709],"iteration":485,"passed_time":9.647552044,"remaining_time":10.20337809},
{"learn":[0.07055306993],"iteration":486,"passed_time":9.663251424,"remaining_time":10.17915396},
{"learn":[0.07054054409],"iteration":487,"passed_time":9.679628453,"remaining_time":10.15567575},
{"learn":[0.07051068595],"iteration":488,"passed_time":9.697092462,"remaining_time":10.13336247},
{"learn":[0.07047130372],"iteration":489,"passed_time":9.713251355,"remaining_time":10.10971059},
{"learn":[0.07046660578],"iteration":490,"passed_time":9.728551082,"remaining_time":10.08519858},
{"learn":[0.07043364104],"iteration":491,"passed_time":9.747316119,"remaining_time":10.06430201},
{"learn":[0.0704118229],"iteration":492,"passed_time":9.763062015,"remaining_time":10.04030921},
{"learn":[0.07038604659],"iteration":493,"passed_time":9.780598819,"remaining_time":10.01818422},
{"learn":[0.07036101868],"iteration":494,"passed_time":9.799120845,"remaining_time":9.997082882},
{"learn":[0.07035271242],"iteration":495,"passed_time":9.816905009,"remaining_time":9.975242187},
{"learn":[0.07034026188],"iteration":496,"passed_time":9.835715241,"remaining_time":9.95445627},
{"learn":[0.07032806983],"iteration":497,"passed_time":9.854888186,"remaining_time":9.934043915},
{"learn":[0.07032349309],"iteration":498,"passed_time":9.868646929,"remaining_time":9.908200624},
{"learn":[0.07031178815],"iteration":499,"passed_time":9.886091672,"remaining_time":9.886091672},
{"learn":[0.07029752738],"iteration":500,"passed_time":9.901452332,"remaining_time":9.861925576},
{"learn":[0.07025398495],"iteration":501,"passed_time":9.920620559,"remaining_time":9.841571789},
{"learn":[0.07024121349],"iteration":502,"passed_time":9.939127616,"remaining_time":9.820569434},
{"learn":[0.07021462958],"iteration":503,"passed_time":9.95643272,"remaining_time":9.798394106},
{"learn":[0.07020936343],"iteration":504,"passed_time":9.972357909,"remaining_time":9.774885476},
{"learn":[0.07018767278],"iteration":505,"passed_time":9.987431315,"remaining_time":9.750575237},
{"learn":[0.07015923664],"iteration":506,"passed_time":10.00324837,"remaining_time":9.727024552},
{"learn":[0.07011919191],"iteration":507,"passed_time":10.02278487,"remaining_time":9.707106611},
{"learn":[0.07007577623],"iteration":508,"passed_time":10.040629,"remaining_time":9.685557641},
{"learn":[0.07003647284],"iteration":509,"passed_time":10.05843219,"remaining_time":9.663983869},
{"learn":[0.07000058293],"iteration":510,"passed_time":10.07783164,"remaining_time":9.643952388},
{"learn":[0.06998057492],"iteration":511,"passed_time":10.09259626,"remaining_time":9.619505809},
{"learn":[0.06995557024],"iteration":512,"passed_time":10.10701788,"remaining_time":9.594771363},
{"learn":[0.0698959718],"iteration":513,"passed_time":10.12136946,"remaining_time":9.57001081},
{"learn":[0.06986213972],"iteration":514,"passed_time":10.14091812,"remaining_time":9.550185027},
{"learn":[0.06983278029],"iteration":515,"passed_time":10.15837682,"remaining_time":9.528399963},
{"learn":[0.06979493147],"iteration":516,"passed_time":10.17400288,"remaining_time":9.504919522},
{"learn":[0.06978200967],"iteration":517,"passed_time":10.19030985,"remaining_time":9.48210299},
{"learn":[0.06973327667],"iteration":518,"passed_time":10.20670839,"remaining_time":9.459396409},
{"learn":[0.06968830865],"iteration":519,"passed_time":10.22661426,"remaining_time":9.439951623},
{"learn":[0.06964807517],"iteration":520,"passed_time":10.247509,"remaining_time":9.421414229},
{"learn":[0.06961518983],"iteration":521,"passed_time":10.26960202,"remaining_time":9.403965066},
{"learn":[0.06955846363],"iteration":522,"passed_time":10.28434493,"remaining_time":9.379794515},
{"learn":[0.06950463271],"iteration":523,"passed_time":10.30109227,"remaining_time":9.357480761},
{"learn":[0.06948611752],"iteration":524,"passed_time":10.32013282,"remaining_time":9.337263024},
{"learn":[0.06946433914],"iteration":525,"passed_time":10.33938072,"remaining_time":9.317236619},
{"learn":[0.06946148583],"iteration":526,"passed_time":10.35473902,"remaining_time":9.293722115},
{"learn":[0.06942071925],"iteration":527,"passed_time":10.37293966,"remaining_time":9.272779397},
{"learn":[0.06940245267],"iteration":528,"passed_time":10.38681639,"remaining_time":9.247997198},
{"learn":[0.0693718324],"iteration":529,"passed_time":10.40130452,"remaining_time":9.223798351},
{"learn":[0.06934575554],"iteration":530,"passed_time":10.4231689,"remaining_time":9.206151064},
{"learn":[0.06933049005],"iteration":531,"passed_time":10.44160379,"remaining_time":9.185470999},
{"learn":[0.06931184312],"iteration":532,"passed_time":10.46013433,"remaining_time":9.164883172},
{"learn":[0.06928561121],"iteration":533,"passed_time":10.4776459,"remaining_time":9.143413842},
{"learn":[0.06926772208],"iteration":534,"passed_time":10.49380969,"remaining_time":9.120787859},
{"learn":[0.06925531375],"iteration":535,"passed_time":10.51028494,"remaining_time":9.098455619},
{"learn":[0.06923997982],"iteration":536,"passed_time":10.52646744,"remaining_time":9.07589278},
{"learn":[0.0691951437],"iteration":537,"passed_time":10.54287616,"remaining_time":9.053547932},
{"learn":[0.06915888041],"iteration":538,"passed_time":10.56203736,"remaining_time":9.033579261},
{"learn":[0.06912444475],"iteration":539,"passed_time":10.57864029,"remaining_time":9.011434318},
{"learn":[0.0690483316],"iteration":540,"passed_time":10.59531279,"remaining_time":8.989368896},
{"learn":[0.06900282032],"iteration":541,"passed_time":10.6143778,"remaining_time":8.969345077},
{"learn":[0.06898126101],"iteration":542,"passed_time":10.63155711,"remaining_time":8.947737751},
{"learn":[0.06895987003],"iteration":543,"passed_time":10.6489828,"remaining_time":8.926353227},
{"learn":[0.06891801171],"iteration":544,"passed_time":10.67110248,"remaining_time":8.90890207},
{"learn":[0.06885679467],"iteration":545,"passed_time":10.6929288,"remaining_time":8.891189879},
{"learn":[0.06881942875],"iteration":546,"passed_time":10.71163395,"remaining_time":8.870877844},
{"learn":[0.06880057041],"iteration":547,"passed_time":10.72723194,"remaining_time":8.848008829},
{"learn":[0.06871493091],"iteration":548,"passed_time":10.74528659,"remaining_time":8.827184431},
{"learn":[0.06870694934],"iteration":549,"passed_time":10.76172769,"remaining_time":8.805049927},
{"learn":[0.06866201791],"iteration":550,"passed_time":10.77943601,"remaining_time":8.783968728},
{"learn":[0.06860018412],"iteration":551,"passed_time":10.79553316,"remaining_time":8.76159213},
{"learn":[0.06854461059],"iteration":552,"passed_time":10.8137284,"remaining_time":8.740934167},
{"learn":[0.06851164062],"iteration":553,"passed_time":10.82762001,"remaining_time":8.71682044},
{"learn":[0.06848905126],"iteration":554,"passed_time":10.84546451,"remaining_time":8.695912989},
{"learn":[0.06848691782],"iteration":555,"passed_time":10.8637678,"remaining_time":8.675382922},
{"learn":[0.06846738945],"iteration":556,"passed_time":10.88585005,"remaining_time":8.657866375},
{"learn":[0.06844539462],"iteration":557,"passed_time":10.90455099,"remaining_time":8.637655089},
{"learn":[0.0684011818],"iteration":558,"passed_time":10.92259783,"remaining_time":8.61693317},
{"learn":[0.0683722086],"iteration":559,"passed_time":10.93915051,"remaining_time":8.595046831},
{"learn":[0.06834081028],"iteration":560,"passed_time":10.95725368,"remaining_time":8.574392808},
{"learn":[0.06829955806],"iteration":561,"passed_time":10.97472798,"remaining_time":8.553257748},
{"learn":[0.06827690974],"iteration":562,"passed_time":10.99178599,"remaining_time":8.531812573},
{"learn":[0.06822214724],"iteration":563,"passed_time":11.0120031,"remaining_time":8.512825091},
{"learn":[0.06821221883],"iteration":564,"passed_time":11.02542026,"remaining_time":8.488597897},
{"learn":[0.06818596971],"iteration":565,"passed_time":11.04258683,"remaining_time":8.467283897},
{"learn":[0.06814997473],"iteration":566,"passed_time":11.06226609,"remaining_time":8.44790338},
{"learn":[0.06814780689],"iteration":567,"passed_time":11.07923366,"remaining_time":8.4264594},
{"learn":[0.06812138369],"iteration":568,"passed_time":11.123006,"remaining_time":8.425334951},
{"learn":[0.06809815985],"iteration":569,"passed_time":11.14682434,"remaining_time":8.409007837},
{"learn":[0.06809001613],"iteration":570,"passed_time":11.16469615,"remaining_time":8.388186774},
{"learn":[0.06807926965],"iteration":571,"passed_time":11.18249933,"remaining_time":8.367324673},
{"learn":[0.06805983292],"iteration":572,"passed_time":11.19997214,"remaining_time":8.346227061},
{"learn":[0.06804420037],"iteration":573,"passed_time":11.21727978,"remaining_time":8.325019491},
{"learn":[0.06801541329],"iteration":574,"passed_time":11.23411394,"remaining_time":8.303475522},
{"learn":[0.06796770082],"iteration":575,"passed_time":11.25196263,"remaining_time":8.282694711},
{"learn":[0.06794198426],"iteration":576,"passed_time":11.26976483,"remaining_time":8.261889991},
{"learn":[0.06791258712],"iteration":577,"passed_time":11.28788157,"remaining_time":8.241325295},
{"learn":[0.06787732741],"iteration":578,"passed_time":11.30765329,"remaining_time":8.22197243},
{"learn":[0.06784274745],"iteration":579,"passed_time":11.3294429,"remaining_time":8.204079344},
{"learn":[0.06778179868],"iteration":580,"passed_time":11.34852791,"remaining_time":8.184222362},
{"learn":[0.06775295052],"iteration":581,"passed_time":11.36709073,"remaining_time":8.163992996},
{"learn":[0.06773489787],"iteration":582,"passed_time":11.38275262,"remaining_time":8.14169441},
{"learn":[0.06768578434],"iteration":583,"passed_time":11.39981344,"remaining_time":8.12041505},
{"learn":[0.06761425594],"iteration":584,"passed_time":11.41781895,"remaining_time":8.099820282},
{"learn":[0.06757331171],"iteration":585,"passed_time":11.43681363,"remaining_time":8.079933176},
{"learn":[0.06755884874],"iteration":586,"passed_time":11.45479023,"remaining_time":8.059332818},
{"learn":[0.0675127748],"iteration":587,"passed_time":11.4761958,"remaining_time":8.041143998},
{"learn":[0.06748636498],"iteration":588,"passed_time":11.49563652,"remaining_time":8.021573189},
{"learn":[0.06747661014],"iteration":589,"passed_time":11.51465494,"remaining_time":8.001709368},
{"learn":[0.06744906764],"iteration":590,"passed_time":11.53386827,"remaining_time":7.98198329},
{"learn":[0.0674012122],"iteration":591,"passed_time":11.55339114,"remaining_time":7.962472273},
{"learn":[0.06736105374],"iteration":592,"passed_time":11.57183019,"remaining_time":7.94221735},
{"learn":[0.06730037096],"iteration":593,"passed_time":11.58933752,"remaining_time":7.921331707},
{"learn":[0.06728275522],"iteration":594,"passed_time":11.60722542,"remaining_time":7.900716462},
{"learn":[0.06726533667],"iteration":595,"passed_time":11.62294649,"remaining_time":7.87864158},
{"learn":[0.0672232424],"iteration":596,"passed_time":11.64105942,"remaining_time":7.858202593},
{"learn":[0.06719804559],"iteration":597,"passed_time":11.6597587,"remaining_time":7.838165547},
{"learn":[0.06716869745],"iteration":598,"passed_time":11.67860854,"remaining_time":7.818233767},
{"learn":[0.06714218978],"iteration":599,"passed_time":11.70231483,"remaining_time":7.801543217},
{"learn":[0.06711432618],"iteration":600,"passed_time":11.721803,"remaining_time":7.782028945},
{"learn":[0.06710569782],"iteration":601,"passed_time":11.74104519,"remaining_time":7.762352136},
{"learn":[0.06707578351],"iteration":602,"passed_time":11.76059009,"remaining_time":7.742876061},
{"learn":[0.06707203402],"iteration":603,"passed_time":11.77629435,"remaining_time":7.720881724},
{"learn":[0.06704703094],"iteration":604,"passed_time":11.79535455,"remaining_time":7.701099253},
{"learn":[0.06702182886],"iteration":605,"passed_time":11.81291069,"remaining_time":7.680341275},
{"learn":[0.0669997475],"iteration":606,"passed_time":11.83164753,"remaining_time":7.660358284},
{"learn":[0.06697003554],"iteration":607,"passed_time":11.85263877,"remaining_time":7.641832893},
{"learn":[0.06694999447],"iteration":608,"passed_time":11.87319596,"remaining_time":7.623020724},
{"learn":[0.06692841202],"iteration":609,"passed_time":11.89213169,"remaining_time":7.60316616},
{"learn":[0.06689538429],"iteration":610,"passed_time":11.91256195,"remaining_time":7.584266117},
{"learn":[0.06687650074],"iteration":611,"passed_time":11.93303283,"remaining_time":7.565386824},
{"learn":[0.06685669101],"iteration":612,"passed_time":11.95412237,"remaining_time":7.546892918},
{"learn":[0.06684047121],"iteration":613,"passed_time":11.97580435,"remaining_time":7.528762997},
{"learn":[0.0668080301],"iteration":614,"passed_time":11.99283727,"remaining_time":7.507711137},
{"learn":[0.06679500411],"iteration":615,"passed_time":12.01085522,"remaining_time":7.48728637},
{"learn":[0.06677777399],"iteration":616,"passed_time":12.02821599,"remaining_time":7.466461463},
{"learn":[0.06675699661],"iteration":617,"passed_time":12.04926758,"remaining_time":7.447929154},
{"learn":[0.06675515684],"iteration":618,"passed_time":12.06555914,"remaining_time":7.426458859},
{"learn":[0.06671631066],"iteration":619,"passed_time":12.08386948,"remaining_time":7.406242582},
{"learn":[0.06666421908],"iteration":620,"passed_time":12.10728792,"remaining_time":7.389149956},
{"learn":[0.06664607468],"iteration":621,"passed_time":12.13028006,"remaining_time":7.371777912},
{"learn":[0.06661244358],"iteration":622,"passed_time":12.15240642,"remaining_time":7.353863918},
{"learn":[0.06657157594],"iteration":623,"passed_time":12.171318,"remaining_time":7.333999308},
{"learn":[0.06652240163],"iteration":624,"passed_time":12.18946513,"remaining_time":7.313679078},
{"learn":[0.06649449901],"iteration":625,"passed_time":12.20724424,"remaining_time":7.293145922},
{"learn":[0.06646077538],"iteration":626,"passed_time":12.22466967,"remaining_time":7.272411144},
{"learn":[0.06641429364],"iteration":627,"passed_time":12.24311122,"remaining_time":7.252288811},
{"learn":[0.06638635739],"iteration":628,"passed_time":12.26160101,"remaining_time":7.23220028},
{"learn":[0.06634325804],"iteration":629,"passed_time":12.2789011,"remaining_time":7.211418105},
{"learn":[0.06631651141],"iteration":630,"passed_time":12.29672499,"remaining_time":7.19095328},
{"learn":[0.06630198581],"iteration":631,"passed_time":12.31749974,"remaining_time":7.172215038},
{"learn":[0.06628657256],"iteration":632,"passed_time":12.33582315,"remaining_time":7.152049122},
{"learn":[0.06623894329],"iteration":633,"passed_time":12.36002059,"remaining_time":7.135280025},
{"learn":[0.06621099322],"iteration":634,"passed_time":12.38085104,"remaining_time":7.11655217},
{"learn":[0.06617955116],"iteration":635,"passed_time":12.4000022,"remaining_time":7.096856605},
{"learn":[0.06614983341],"iteration":636,"passed_time":12.41888891,"remaining_time":7.07701205},
{"learn":[0.06611354242],"iteration":637,"passed_time":12.4370288,"remaining_time":7.056746748},
{"learn":[0.06608013073],"iteration":638,"passed_time":12.45825803,"remaining_time":7.038233408},
{"learn":[0.06605594496],"iteration":639,"passed_time":12.47978889,"remaining_time":7.019881253},
{"learn":[0.06600732512],"iteration":640,"passed_time":12.49676424,"remaining_time":6.998967801},
{"learn":[0.06597743262],"iteration":641,"passed_time":12.51400075,"remaining_time":6.978212257},
{"learn":[0.06595248417],"iteration":642,"passed_time":12.53297212,"remaining_time":6.958430868},
{"learn":[0.06592955683],"iteration":643,"passed_time":12.55770069,"remaining_time":6.941834545},
{"learn":[0.06587384515],"iteration":644,"passed_time":12.57527198,"remaining_time":6.921273727},
{"learn":[0.06586965413],"iteration":645,"passed_time":12.59515872,"remaining_time":6.901990999},
{"learn":[0.06582379374],"iteration":646,"passed_time":12.61266547,"remaining_time":6.881407901},
{"learn":[0.06580177863],"iteration":647,"passed_time":12.63178205,"remaining_time":6.86170877},
{"learn":[0.06577364679],"iteration":648,"passed_time":12.64765603,"remaining_time":6.840257729},
{"learn":[0.06574608826],"iteration":649,"passed_time":12.66403123,"remaining_time":6.819093741},
{"learn":[0.06571856973],"iteration":650,"passed_time":12.67915245,"remaining_time":6.797272204},
{"learn":[0.0656843755],"iteration":651,"passed_time":12.69604299,"remaining_time":6.776415585},
{"learn":[0.06561886745],"iteration":652,"passed_time":12.7114757,"remaining_time":6.754796426},
{"learn":[0.06558360529],"iteration":653,"passed_time":12.72894589,"remaining_time":6.734274123},
{"learn":[0.0655711492],"iteration":654,"passed_time":12.74715019,"remaining_time":6.714147811},
{"learn":[0.06555200794],"iteration":655,"passed_time":12.76804384,"remaining_time":6.695437621},
{"learn":[0.06552715859],"iteration":656,"passed_time":12.78761261,"remaining_time":6.676029108},
{"learn":[0.06547195448],"iteration":657,"passed_time":12.80406538,"remaining_time":6.655000545},
{"learn":[0.06541709259],"iteration":658,"passed_time":12.82035399,"remaining_time":6.633900927},
{"learn":[0.06537194542],"iteration":659,"passed_time":12.84169399,"remaining_time":6.615418118},
{"learn":[0.06534420131],"iteration":660,"passed_time":12.86015848,"remaining_time":6.59545193},
{"learn":[0.06531500614],"iteration":661,"passed_time":12.87548064,"remaining_time":6.573885886},
{"learn":[0.06528524304],"iteration":662,"passed_time":12.89265738,"remaining_time":6.553281351},
{"learn":[0.06524764928],"iteration":663,"passed_time":12.9084091,"remaining_time":6.531966052},
{"learn":[0.06521885772],"iteration":664,"passed_time":12.92475076,"remaining_time":6.510964667},
{"learn":[0.06516736359],"iteration":665,"passed_time":12.94100617,"remaining_time":6.489934025},
{"learn":[0.06515036902],"iteration":666,"passed_time":12.95929402,"remaining_time":6.469932396},
{"learn":[0.06512268634],"iteration":667,"passed_time":12.97818376,"remaining_time":6.450235042},
{"learn":[0.06509756009],"iteration":668,"passed_time":12.99774274,"remaining_time":6.430871222},
{"learn":[0.0650478606],"iteration":669,"passed_time":13.0121849,"remaining_time":6.408986594},
{"learn":[0.06502205846],"iteration":670,"passed_time":13.02836764,"remaining_time":6.387977577},
{"learn":[0.06499205163],"iteration":671,"passed_time":13.04556215,"remaining_time":6.367476764},
{"learn":[0.06495576484],"iteration":672,"passed_time":13.05844866,"remaining_time":6.344892589},
{"learn":[0.06493495903],"iteration":673,"passed_time":13.07231642,"remaining_time":6.322811798},
{"learn":[0.06487867059],"iteration":674,"passed_time":13.0894359,"remaining_time":6.302320987},
{"learn":[0.06485998937],"iteration":675,"passed_time":13.10745031,"remaining_time":6.282269082},
{"learn":[0.06484574246],"iteration":676,"passed_time":13.12342812,"remaining_time":6.261251528},
{"learn":[0.06483328107],"iteration":677,"passed_time":13.17255266,"remaining_time":6.255991086},
{"learn":[0.06482835279],"iteration":678,"passed_time":13.22145311,"remaining_time":6.250495504},
{"learn":[0.06482331282],"iteration":679,"passed_time":13.23982152,"remaining_time":6.230504243},
{"learn":[0.06477615168],"iteration":680,"passed_time":13.26675518,"remaining_time":6.214529958},
{"learn":[0.06475269991],"iteration":681,"passed_time":13.28504681,"remaining_time":6.194493969},
{"learn":[0.06473787657],"iteration":682,"passed_time":13.30190424,"remaining_time":6.173797427},
{"learn":[0.06471380678],"iteration":683,"passed_time":13.31712174,"remaining_time":6.152354488},
{"learn":[0.0646792695],"iteration":684,"passed_time":13.33455252,"remaining_time":6.131947508},
{"learn":[0.06467123691],"iteration":685,"passed_time":13.34895327,"remaining_time":6.110162285},
{"learn":[0.06463281786],"iteration":686,"passed_time":13.36289972,"remaining_time":6.088191577},
{"learn":[0.0646213885],"iteration":687,"passed_time":13.37854845,"remaining_time":6.067016157},
{"learn":[0.06458528261],"iteration":688,"passed_time":13.39617739,"remaining_time":6.046750605},
{"learn":[0.06454758256],"iteration":689,"passed_time":13.4139614,"remaining_time":6.026562368},
{"learn":[0.06452794136],"iteration":690,"passed_time":13.43287498,"remaining_time":6.006886208},
{"learn":[0.06443297564],"iteration":691,"passed_time":13.45006826,"remaining_time":5.986446566},
{"learn":[0.06442513313],"iteration":692,"passed_time":13.46507895,"remaining_time":5.965049404},
{"learn":[0.06440391269],"iteration":693,"passed_time":13.48188823,"remaining_time":5.944463687},
{"learn":[0.06439794789],"iteration":694,"passed_time":13.49673236,"remaining_time":5.923026431},
{"learn":[0.06436689377],"iteration":695,"passed_time":13.51318301,"remaining_time":5.902309819},
{"learn":[0.0643551868],"iteration":696,"passed_time":13.52926676,"remaining_time":5.881445951},
{"learn":[0.06433092548],"iteration":697,"passed_time":13.54624302,"remaining_time":5.860981938},
{"learn":[0.06431926808],"iteration":698,"passed_time":13.55965322,"remaining_time":5.838992301},
{"learn":[0.06429324559],"iteration":699,"passed_time":13.57517516,"remaining_time":5.81793221},
{"learn":[0.06427348214],"iteration":700,"passed_time":13.59145752,"remaining_time":5.797212266},
{"learn":[0.06424952935],"iteration":701,"passed_time":13.6077841,"remaining_time":5.776523737},
{"learn":[0.06422466281],"iteration":702,"passed_time":13.62758298,"remaining_time":5.757314575},
{"learn":[0.06417966745],"iteration":703,"passed_time":13.64603756,"remaining_time":5.737538521},
{"learn":[0.06415770152],"iteration":704,"passed_time":13.66144823,"remaining_time":5.71649252},
{"learn":[0.06413994312],"iteration":705,"passed_time":13.67819205,"remaining_time":5.696017651},
{"learn":[0.06411295969],"iteration":706,"passed_time":13.69494219,"remaining_time":5.675555957},
{"learn":[0.06409156791],"iteration":707,"passed_time":13.71176772,"remaining_time":5.65513584},
{"learn":[0.06407273694],"iteration":708,"passed_time":13.72836162,"remaining_time":5.634630794},
{"learn":[0.06404888622],"iteration":709,"passed_time":13.74460863,"remaining_time":5.613995075},
{"learn":[0.06403890943],"iteration":710,"passed_time":13.75816611,"remaining_time":5.592278489},
{"learn":[0.06402370534],"iteration":711,"passed_time":13.7742812,"remaining_time":5.571619362},
{"learn":[0.06400512263],"iteration":712,"passed_time":13.79123209,"remaining_time":5.55130941},
{"learn":[0.06397388313],"iteration":713,"passed_time":13.80888852,"remaining_time":5.531291482},
{"learn":[0.06395533078],"iteration":714,"passed_time":13.82638266,"remaining_time":5.511215466},
{"learn":[0.06394318228],"iteration":715,"passed_time":13.84547412,"remaining_time":5.491780239},
{"learn":[0.06393190525],"iteration":716,"passed_time":13.8598701,"remaining_time":5.470492662},
{"learn":[0.06390902836],"iteration":717,"passed_time":13.87661456,"remaining_time":5.450146666},
{"learn":[0.06388280031],"iteration":718,"passed_time":13.89115466,"remaining_time":5.428949177},
{"learn":[0.06383378465],"iteration":719,"passed_time":13.90795942,"remaining_time":5.408650886},
{"learn":[0.06379630501],"iteration":720,"passed_time":13.92536699,"remaining_time":5.38859555},
{"learn":[0.06376664946],"iteration":721,"passed_time":13.9427022,"remaining_time":5.368519685},
{"learn":[0.06372673188],"iteration":722,"passed_time":13.95909246,"remaining_time":5.348089365},
{"learn":[0.06368486815],"iteration":723,"passed_time":13.97595223,"remaining_time":5.327849194},
{"learn":[0.06366836065],"iteration":724,"passed_time":13.99223582,"remaining_time":5.307399794},
{"learn":[0.06365406851],"iteration":725,"passed_time":14.00853293,"remaining_time":5.286966974},
{"learn":[0.06363553804],"iteration":726,"passed_time":14.02691556,"remaining_time":5.267328675},
{"learn":[0.06359708196],"iteration":727,"passed_time":14.04431814,"remaining_time":5.247327657},
{"learn":[0.06358504045],"iteration":728,"passed_time":14.05844709,"remaining_time":5.22611682},
{"learn":[0.06355075792],"iteration":729,"passed_time":14.0752985,"remaining_time":5.205932323},
{"learn":[0.06354245362],"iteration":730,"passed_time":14.08901745,"remaining_time":5.184604233},
{"learn":[0.06350118168],"iteration":731,"passed_time":14.1056908,"remaining_time":5.164378599},
{"learn":[0.0634767786],"iteration":732,"passed_time":14.12222888,"remaining_time":5.144113384},
{"learn":[0.0634399244],"iteration":733,"passed_time":14.13789616,"remaining_time":5.12354275},
{"learn":[0.06341159954],"iteration":734,"passed_time":14.15257918,"remaining_time":5.102630588},
{"learn":[0.06340909507],"iteration":735,"passed_time":14.16596797,"remaining_time":5.081271121},
{"learn":[0.06338095491],"iteration":736,"passed_time":14.18293496,"remaining_time":5.061210169},
{"learn":[0.06334421187],"iteration":737,"passed_time":14.19826897,"remaining_time":5.040577873},
{"learn":[0.06330537121],"iteration":738,"passed_time":14.21633805,"remaining_time":5.020925889},
{"learn":[0.06327341005],"iteration":739,"passed_time":14.23364979,"remaining_time":5.001012088},
{"learn":[0.06315032977],"iteration":740,"passed_time":14.25064378,"remaining_time":4.980994248},
{"learn":[0.06312553969],"iteration":741,"passed_time":14.26547036,"remaining_time":4.960230935},
{"learn":[0.06309388814],"iteration":742,"passed_time":14.28469385,"remaining_time":4.941004468},
{"learn":[0.06305242891],"iteration":743,"passed_time":14.30089494,"remaining_time":4.920738045},
{"learn":[0.06301701639],"iteration":744,"passed_time":14.31711606,"remaining_time":4.900489391},
{"learn":[0.06300743701],"iteration":745,"passed_time":14.32960115,"remaining_time":4.878979479},
{"learn":[0.06299613834],"iteration":746,"passed_time":14.34587316,"remaining_time":4.858776318},
{"learn":[0.06298819901],"iteration":747,"passed_time":14.35656142,"remaining_time":4.83670251},
{"learn":[0.06296930824],"iteration":748,"passed_time":14.37189414,"remaining_time":4.816215525},
{"learn":[0.06294022586],"iteration":749,"passed_time":14.38626001,"remaining_time":4.795420002},
{"learn":[0.06291476942],"iteration":750,"passed_time":14.40306176,"remaining_time":4.77544924},
{"learn":[0.0629092133],"iteration":751,"passed_time":14.42082144,"remaining_time":4.755802816},
{"learn":[0.06288520751],"iteration":752,"passed_time":14.43849504,"remaining_time":4.736133168},
{"learn":[0.0628584349],"iteration":753,"passed_time":14.45402825,"remaining_time":4.715770491},
{"learn":[0.06284517183],"iteration":754,"passed_time":14.47023496,"remaining_time":4.695639161},
{"learn":[0.0628369957],"iteration":755,"passed_time":14.48383779,"remaining_time":4.674677804},
{"learn":[0.06283064921],"iteration":756,"passed_time":14.4995395,"remaining_time":4.654409642},
{"learn":[0.06279090516],"iteration":757,"passed_time":14.51742087,"remaining_time":4.634849406},
{"learn":[0.0627300268],"iteration":758,"passed_time":14.53282885,"remaining_time":4.614508239},
{"learn":[0.06269592138],"iteration":759,"passed_time":14.54732144,"remaining_time":4.593890981},
{"learn":[0.06268333348],"iteration":760,"passed_time":14.56285122,"remaining_time":4.573615562},
{"learn":[0.06266245363],"iteration":761,"passed_time":14.57842606,"remaining_time":4.55336667},
{"learn":[0.0626489861],"iteration":762,"passed_time":14.59371012,"remaining_time":4.53303971},
{"learn":[0.06262163395],"iteration":763,"passed_time":14.60859695,"remaining_time":4.512603246},
{"learn":[0.06261051296],"iteration":764,"passed_time":14.62743497,"remaining_time":4.493395057},
{"learn":[0.06260275865],"iteration":765,"passed_time":14.64647093,"remaining_time":4.474248301},
{"learn":[0.06259303122],"iteration":766,"passed_time":14.66440804,"remaining_time":4.454768023},
{"learn":[0.06256231021],"iteration":767,"passed_time":14.6796002,"remaining_time":4.43446256},
{"learn":[0.06253235255],"iteration":768,"passed_time":14.69510841,"remaining_time":4.414265336},
{"learn":[0.06251759254],"iteration":769,"passed_time":14.71265562,"remaining_time":4.39468934},
{"learn":[0.06250294677],"iteration":770,"passed_time":14.72858568,"remaining_time":4.37463829},
{"learn":[0.06249328381],"iteration":771,"passed_time":14.74358807,"remaining_time":4.354323937},
{"learn":[0.06247534821],"iteration":772,"passed_time":14.75942779,"remaining_time":4.334269221},
{"learn":[0.06243709303],"iteration":773,"passed_time":14.77557905,"remaining_time":4.314316363},
{"learn":[0.06241050659],"iteration":774,"passed_time":14.79180237,"remaining_time":4.294394237},
{"learn":[0.06240886347],"iteration":775,"passed_time":14.80541479,"remaining_time":4.273727981},
{"learn":[0.06237304524],"iteration":776,"passed_time":14.82455853,"remaining_time":4.254667378},
{"learn":[0.0623621592],"iteration":777,"passed_time":14.84197419,"remaining_time":4.235113458},
{"learn":[0.06234345642],"iteration":778,"passed_time":14.8589588,"remaining_time":4.21544274},
{"learn":[0.06231480654],"iteration":779,"passed_time":14.87609491,"remaining_time":4.195821641},
{"learn":[0.06229824401],"iteration":780,"passed_time":14.89128255,"remaining_time":4.175660535},
{"learn":[0.06227396289],"iteration":781,"passed_time":14.90986078,"remaining_time":4.156457352},
{"learn":[0.0622535965],"iteration":782,"passed_time":14.92620789,"remaining_time":4.136637436},
{"learn":[0.06224527076],"iteration":783,"passed_time":14.94129403,"remaining_time":4.116478968},
{"learn":[0.06223066271],"iteration":784,"passed_time":14.95757081,"remaining_time":4.096659522},
{"learn":[0.06220125012],"iteration":785,"passed_time":14.97379343,"remaining_time":4.076834342},
{"learn":[0.06218818759],"iteration":786,"passed_time":14.989345,"remaining_time":4.056836703},
{"learn":[0.06216847383],"iteration":787,"passed_time":15.00529206,"remaining_time":4.036956747},
{"learn":[0.06213563178],"iteration":788,"passed_time":15.02365867,"remaining_time":4.017733813},
{"learn":[0.06212994572],"iteration":789,"passed_time":15.04424458,"remaining_time":3.999102989},
{"learn":[0.06211065642],"iteration":790,"passed_time":15.06346796,"remaining_time":3.98010721},
{"learn":[0.06208422523],"iteration":791,"passed_time":15.08701453,"remaining_time":3.962246241},
{"learn":[0.06204512345],"iteration":792,"passed_time":15.1042696,"remaining_time":3.942728635},
{"learn":[0.06202346134],"iteration":793,"passed_time":15.12139592,"remaining_time":3.923183325},
{"learn":[0.06200016318],"iteration":794,"passed_time":15.13768492,"remaining_time":3.903428187},
{"learn":[0.06197361641],"iteration":795,"passed_time":15.15548533,"remaining_time":3.884069106},
{"learn":[0.06196391725],"iteration":796,"passed_time":15.17116899,"remaining_time":3.864174788},
{"learn":[0.06194077164],"iteration":797,"passed_time":15.18752397,"remaining_time":3.844460955},
{"learn":[0.06192863141],"iteration":798,"passed_time":15.20416628,"remaining_time":3.824827814},
{"learn":[0.06190466613],"iteration":799,"passed_time":15.22168626,"remaining_time":3.805421564},
{"learn":[0.06186200461],"iteration":800,"passed_time":15.24163504,"remaining_time":3.786623438},
{"learn":[0.06183731623],"iteration":801,"passed_time":15.26031733,"remaining_time":3.767509764},
{"learn":[0.06182919213],"iteration":802,"passed_time":15.27714813,"remaining_time":3.747942941},
{"learn":[0.06182463543],"iteration":803,"passed_time":15.2896212,"remaining_time":3.727320592},
{"learn":[0.06180417136],"iteration":804,"passed_time":15.31419758,"remaining_time":3.709650346},
{"learn":[0.06179661003],"iteration":805,"passed_time":15.33253967,"remaining_time":3.690462403},
{"learn":[0.06177275646],"iteration":806,"passed_time":15.35455515,"remaining_time":3.672155074},
{"learn":[0.06176583781],"iteration":807,"passed_time":15.37518291,"remaining_time":3.653508811},
{"learn":[0.06173409486],"iteration":808,"passed_time":15.39915034,"remaining_time":3.635646124},
{"learn":[0.06170596325],"iteration":809,"passed_time":15.43748766,"remaining_time":3.621139081},
{"learn":[0.06168843822],"iteration":810,"passed_time":15.46713382,"remaining_time":3.604547833},
{"learn":[0.06167956659],"iteration":811,"passed_time":15.48819762,"remaining_time":3.585937381},
{"learn":[0.06165363102],"iteration":812,"passed_time":15.51893499,"remaining_time":3.569545933},
{"learn":[0.06162384466],"iteration":813,"passed_time":15.53465657,"remaining_time":3.549688112},
{"learn":[0.06161304131],"iteration":814,"passed_time":15.54975319,"remaining_time":3.529698578},
{"learn":[0.06158982336],"iteration":815,"passed_time":15.56500657,"remaining_time":3.509756384},
{"learn":[0.06157093499],"iteration":816,"passed_time":15.58150797,"remaining_time":3.490105213},
{"learn":[0.06154784556],"iteration":817,"passed_time":15.59984548,"remaining_time":3.470870265},
{"learn":[0.06151252463],"iteration":818,"passed_time":15.61698942,"remaining_time":3.45137373},
{"learn":[0.06149391774],"iteration":819,"passed_time":15.63468933,"remaining_time":3.432004975},
{"learn":[0.06145861884],"iteration":820,"passed_time":15.65824246,"remaining_time":3.413916443},
{"learn":[0.06143160722],"iteration":821,"passed_time":15.67968155,"remaining_time":3.395356833},
{"learn":[0.06138173659],"iteration":822,"passed_time":15.69786162,"remaining_time":3.376089316},
{"learn":[0.06138036708],"iteration":823,"passed_time":15.71346051,"remaining_time":3.356273118},
{"learn":[0.06136316909],"iteration":824,"passed_time":15.7295959,"remaining_time":3.336580947},
{"learn":[0.06134217753],"iteration":825,"passed_time":15.74621769,"remaining_time":3.316999852},
{"learn":[0.06131488682],"iteration":826,"passed_time":15.76204116,"remaining_time":3.297258912},
{"learn":[0.06124598263],"iteration":827,"passed_time":15.77974967,"remaining_time":3.277919014},
{"learn":[0.06122735602],"iteration":828,"passed_time":15.79549817,"remaining_time":3.258178755},
{"learn":[0.06122300182],"iteration":829,"passed_time":15.81110796,"remaining_time":3.238419702},
{"learn":[0.06119625321],"iteration":830,"passed_time":15.82936473,"remaining_time":3.219208952},
{"learn":[0.06116078465],"iteration":831,"passed_time":15.84625448,"remaining_time":3.199724462},
{"learn":[0.06113338912],"iteration":832,"passed_time":15.86302947,"remaining_time":3.180223195},
{"learn":[0.06111549164],"iteration":833,"passed_time":15.88225566,"remaining_time":3.161216355},
{"learn":[0.06109346293],"iteration":834,"passed_time":15.90057173,"remaining_time":3.142029144},
{"learn":[0.06107470142],"iteration":835,"passed_time":15.91803659,"remaining_time":3.122677034},
{"learn":[0.06105202551],"iteration":836,"passed_time":15.9381466,"remaining_time":3.10384456},
{"learn":[0.06101822242],"iteration":837,"passed_time":15.95638741,"remaining_time":3.084647685},
{"learn":[0.06097774533],"iteration":838,"passed_time":15.97192157,"remaining_time":3.064933698},
{"learn":[0.06094746889],"iteration":839,"passed_time":15.98864076,"remaining_time":3.045455384},
{"learn":[0.06091528646],"iteration":840,"passed_time":16.00667902,"remaining_time":3.026233014},
{"learn":[0.06087613799],"iteration":841,"passed_time":16.02287793,"remaining_time":3.006668305},
{"learn":[0.06084489425],"iteration":842,"passed_time":16.04327431,"remaining_time":2.987893317},
{"learn":[0.06081589349],"iteration":843,"passed_time":16.06349893,"remaining_time":2.96908274},
{"learn":[0.06079507072],"iteration":844,"passed_time":16.08873019,"remaining_time":2.951187195},
{"learn":[0.0607639024],"iteration":845,"passed_time":16.11471933,"remaining_time":2.933412265},
{"learn":[0.06072094512],"iteration":846,"passed_time":16.14291939,"remaining_time":2.916017316},
{"learn":[0.06068420872],"iteration":847,"passed_time":16.16850216,"remaining_time":2.898127746},
{"learn":[0.06066149681],"iteration":848,"passed_time":16.19884476,"remaining_time":2.881066618},
{"learn":[0.06064729155],"iteration":849,"passed_time":16.21994659,"remaining_time":2.862343515},
{"learn":[0.06062178002],"iteration":850,"passed_time":16.24376037,"remaining_time":2.844089653},
{"learn":[0.06058230181],"iteration":851,"passed_time":16.26459821,"remaining_time":2.825305792},
{"learn":[0.06056436819],"iteration":852,"passed_time":16.28426772,"remaining_time":2.806315773},
{"learn":[0.0605577778],"iteration":853,"passed_time":16.30148674,"remaining_time":2.786905227},
{"learn":[0.06054410348],"iteration":854,"passed_time":16.32140489,"remaining_time":2.767957555},
{"learn":[0.06049349035],"iteration":855,"passed_time":16.34058558,"remaining_time":2.748883556},
{"learn":[0.06044985986],"iteration":856,"passed_time":16.35636902,"remaining_time":2.729242438},
{"learn":[0.06042870872],"iteration":857,"passed_time":16.37245574,"remaining_time":2.709660506},
{"learn":[0.06042045325],"iteration":858,"passed_time":16.38984688,"remaining_time":2.690300827},
{"learn":[0.06038546625],"iteration":859,"passed_time":16.40326549,"remaining_time":2.670299033},
{"learn":[0.06036475767],"iteration":860,"passed_time":16.42046546,"remaining_time":2.650922995},
{"learn":[0.06034483055],"iteration":861,"passed_time":16.4373596,"remaining_time":2.631503045},
{"learn":[0.06029606778],"iteration":862,"passed_time":16.45371356,"remaining_time":2.612003196},
{"learn":[0.06028744849],"iteration":863,"passed_time":16.47174926,"remaining_time":2.592775346},
{"learn":[0.06026672756],"iteration":864,"passed_time":16.49303617,"remaining_time":2.574057668},
{"learn":[0.06024469774],"iteration":865,"passed_time":16.51006285,"remaining_time":2.554674852},
{"learn":[0.06022540115],"iteration":866,"passed_time":16.52742636,"remaining_time":2.535349142},
{"learn":[0.06020561707],"iteration":867,"passed_time":16.54657701,"remaining_time":2.51629973},
{"learn":[0.06019725034],"iteration":868,"passed_time":16.56403169,"remaining_time":2.49699442},
{"learn":[0.06018101371],"iteration":869,"passed_time":16.58437203,"remaining_time":2.478124556},
{"learn":[0.06017716356],"iteration":870,"passed_time":16.59731966,"remaining_time":2.458156413},
{"learn":[0.06017410047],"iteration":871,"passed_time":16.61368661,"remaining_time":2.438706291},
{"learn":[0.06014609278],"iteration":872,"passed_time":16.63091845,"remaining_time":2.419389053},
{"learn":[0.06011708838],"iteration":873,"passed_time":16.64531512,"remaining_time":2.399667855},
{"learn":[0.06008391026],"iteration":874,"passed_time":16.66155521,"remaining_time":2.380222172},
{"learn":[0.06005897987],"iteration":875,"passed_time":16.67968049,"remaining_time":2.361050664},
{"learn":[0.06003329928],"iteration":876,"passed_time":16.69658836,"remaining_time":2.341710796},
{"learn":[0.06002119542],"iteration":877,"passed_time":16.71241337,"remaining_time":2.322226004},
{"learn":[0.05998919102],"iteration":878,"passed_time":16.73152527,"remaining_time":2.303202},
{"learn":[0.05997076704],"iteration":879,"passed_time":16.74566899,"remaining_time":2.283500317},
{"learn":[0.05994525465],"iteration":880,"passed_time":16.76225128,"remaining_time":2.264140639},
{"learn":[0.05993589673],"iteration":881,"passed_time":16.77823359,"remaining_time":2.244706988},
{"learn":[0.05991054945],"iteration":882,"passed_time":16.79313775,"remaining_time":2.225138298},
{"learn":[0.05989148674],"iteration":883,"passed_time":16.80917412,"remaining_time":2.20572873},
{"learn":[0.05987696892],"iteration":884,"passed_time":16.82669337,"remaining_time":2.186519477},
{"learn":[0.05985387551],"iteration":885,"passed_time":16.84260657,"remaining_time":2.167107392},
{"learn":[0.05983122009],"iteration":886,"passed_time":16.85976289,"remaining_time":2.147861563},
{"learn":[0.05981047512],"iteration":887,"passed_time":16.87705091,"remaining_time":2.128637052},
{"learn":[0.05978887519],"iteration":888,"passed_time":16.89454858,"remaining_time":2.109443073},
{"learn":[0.05977943407],"iteration":889,"passed_time":16.90983646,"remaining_time":2.089979787},
{"learn":[0.05976039332],"iteration":890,"passed_time":16.92756459,"remaining_time":2.0708244},
{"learn":[0.05971866941],"iteration":891,"passed_time":16.94365631,"remaining_time":2.051474082},
{"learn":[0.0597142686],"iteration":892,"passed_time":16.96047451,"remaining_time":2.03221811},
{"learn":[0.05970276143],"iteration":893,"passed_time":16.97905832,"remaining_time":2.013176937},
{"learn":[0.05968045985],"iteration":894,"passed_time":16.99734002,"remaining_time":1.994101343},
{"learn":[0.05966119428],"iteration":895,"passed_time":17.02679904,"remaining_time":1.976324889},
{"learn":[0.05963506558],"iteration":896,"passed_time":17.05060069,"remaining_time":1.957872766},
{"learn":[0.0596012931],"iteration":897,"passed_time":17.07617758,"remaining_time":1.939610371},
{"learn":[0.05957352063],"iteration":898,"passed_time":17.09787571,"remaining_time":1.920895936},
{"learn":[0.05955925162],"iteration":899,"passed_time":17.12372403,"remaining_time":1.902636003},
{"learn":[0.05952725681],"iteration":900,"passed_time":17.15352839,"remaining_time":1.884793908},
{"learn":[0.05951580968],"iteration":901,"passed_time":17.16637407,"remaining_time":1.86508277},
{"learn":[0.05949816921],"iteration":902,"passed_time":17.18593684,"remaining_time":1.846108387},
{"learn":[0.05947865846],"iteration":903,"passed_time":17.2006873,"remaining_time":1.82662166},
{"learn":[0.05946319589],"iteration":904,"passed_time":17.21519541,"remaining_time":1.80711996},
{"learn":[0.05942456748],"iteration":905,"passed_time":17.23002327,"remaining_time":1.787662458},
{"learn":[0.05937628354],"iteration":906,"passed_time":17.24730098,"remaining_time":1.768466363},
{"learn":[0.05933779552],"iteration":907,"passed_time":17.26102211,"remaining_time":1.748914134},
{"learn":[0.05933669632],"iteration":908,"passed_time":17.27248058,"remaining_time":1.729148221},
{"learn":[0.05933041672],"iteration":909,"passed_time":17.28669553,"remaining_time":1.709673185},
{"learn":[0.05931851649],"iteration":910,"passed_time":17.30444641,"remaining_time":1.690555137},
{"learn":[0.05930205164],"iteration":911,"passed_time":17.32100813,"remaining_time":1.671325346},
{"learn":[0.05927988238],"iteration":912,"passed_time":17.33949908,"remaining_time":1.652285235},
{"learn":[0.05923506354],"iteration":913,"passed_time":17.35413991,"remaining_time":1.632884061},
{"learn":[0.0592079399],"iteration":914,"passed_time":17.37013951,"remaining_time":1.613619518},
{"learn":[0.05917618355],"iteration":915,"passed_time":17.38522106,"remaining_time":1.594277913},
{"learn":[0.05914846655],"iteration":916,"passed_time":17.40007015,"remaining_time":1.574924561},
{"learn":[0.05911912079],"iteration":917,"passed_time":17.41717225,"remaining_time":1.555782271},
{"learn":[0.05908831179],"iteration":918,"passed_time":17.43236306,"remaining_time":1.53647596},
{"learn":[0.05906384484],"iteration":919,"passed_time":17.44858848,"remaining_time":1.517268564},
{"learn":[0.05903291847],"iteration":920,"passed_time":17.46460134,"remaining_time":1.49804941},
{"learn":[0.05895758828],"iteration":921,"passed_time":17.4793429,"remaining_time":1.47872966},
{"learn":[0.05893330293],"iteration":922,"passed_time":17.49342606,"remaining_time":1.459364904},
{"learn":[0.05891961264],"iteration":923,"passed_time":17.51113095,"remaining_time":1.440309472},
{"learn":[0.05889046227],"iteration":924,"passed_time":17.52972234,"remaining_time":1.421328838},
{"learn":[0.05886981742],"iteration":925,"passed_time":17.54629389,"remaining_time":1.402187633},
{"learn":[0.05885198613],"iteration":926,"passed_time":17.56384052,"remaining_time":1.383128758},
{"learn":[0.05883322076],"iteration":927,"passed_time":17.58043317,"remaining_time":1.363999126},
{"learn":[0.0588014132],"iteration":928,"passed_time":17.59678853,"remaining_time":1.34485682},
{"learn":[0.05879332248],"iteration":929,"passed_time":17.61146558,"remaining_time":1.325594184},
{"learn":[0.05876659081],"iteration":930,"passed_time":17.62737122,"remaining_time":1.306432454},
{"learn":[0.05874800838],"iteration":931,"passed_time":17.64172489,"remaining_time":1.287164477},
{"learn":[0.05872003948],"iteration":932,"passed_time":17.65632995,"remaining_time":1.267925087},
{"learn":[0.05869307449],"iteration":933,"passed_time":17.66805403,"remaining_time":1.248492041},
{"learn":[0.0586619118],"iteration":934,"passed_time":17.68306392,"remaining_time":1.229303909},
{"learn":[0.05862241631],"iteration":935,"passed_time":17.69670031,"remaining_time":1.210030791},
{"learn":[0.05857762922],"iteration":936,"passed_time":17.7168098,"remaining_time":1.191204928},
{"learn":[0.05854633225],"iteration":937,"passed_time":17.74216525,"remaining_time":1.172723077},
{"learn":[0.05851250498],"iteration":938,"passed_time":17.76693389,"remaining_time":1.154188464},
{"learn":[0.05849103162],"iteration":939,"passed_time":17.79429246,"remaining_time":1.135805902},
{"learn":[0.05846843891],"iteration":940,"passed_time":17.82963444,"remaining_time":1.117904816},
{"learn":[0.05844946377],"iteration":941,"passed_time":17.85530044,"remaining_time":1.09937094},
{"learn":[0.0584443296],"iteration":942,"passed_time":17.87625801,"remaining_time":1.080537335},
{"learn":[0.05843736125],"iteration":943,"passed_time":17.89726752,"remaining_time":1.061702311},
{"learn":[0.05840997258],"iteration":944,"passed_time":17.91348379,"remaining_time":1.042583713},
{"learn":[0.05838211612],"iteration":945,"passed_time":17.92823677,"remaining_time":1.023387723},
{"learn":[0.0583653343],"iteration":946,"passed_time":17.94566329,"remaining_time":1.004350744},
{"learn":[0.05832745727],"iteration":947,"passed_time":17.96696118,"remaining_time":0.9855295161},
{"learn":[0.0583181072],"iteration":948,"passed_time":17.98457149,"remaining_time":0.9665048956},
{"learn":[0.05829928716],"iteration":949,"passed_time":18.00014355,"remaining_time":0.9473759764},
{"learn":[0.05827889214],"iteration":950,"passed_time":18.01712093,"remaining_time":0.9283269457},
{"learn":[0.05826458099],"iteration":951,"passed_time":18.02875208,"remaining_time":0.9090127101},
{"learn":[0.0582430052],"iteration":952,"passed_time":18.04304358,"remaining_time":0.8898458007},
{"learn":[0.05821584057],"iteration":953,"passed_time":18.05974517,"remaining_time":0.8708053226},
{"learn":[0.05819723541],"iteration":954,"passed_time":18.07752289,"remaining_time":0.8518204504},
{"learn":[0.05819055355],"iteration":955,"passed_time":18.08903885,"remaining_time":0.832549905},
{"learn":[0.058162516],"iteration":956,"passed_time":18.10596222,"remaining_time":0.8135385323},
{"learn":[0.05814646992],"iteration":957,"passed_time":18.12108283,"remaining_time":0.7944524833},
{"learn":[0.05811645583],"iteration":958,"passed_time":18.1375027,"remaining_time":0.7754302511},
{"learn":[0.05810501261],"iteration":959,"passed_time":18.15409707,"remaining_time":0.7564207114},
{"learn":[0.05809624777],"iteration":960,"passed_time":18.17130346,"remaining_time":0.7374410355},
{"learn":[0.05808717639],"iteration":961,"passed_time":18.18730977,"remaining_time":0.7184176418},
{"learn":[0.05801819363],"iteration":962,"passed_time":18.2050972,"remaining_time":0.6994689473},
{"learn":[0.05799868278],"iteration":963,"passed_time":18.22112874,"remaining_time":0.6804570899},
{"learn":[0.05797969611],"iteration":964,"passed_time":18.23744938,"remaining_time":0.6614618945},
{"learn":[0.05795506773],"iteration":965,"passed_time":18.2549118,"remaining_time":0.6425124237},
{"learn":[0.05793396851],"iteration":966,"passed_time":18.27370825,"remaining_time":0.6236115534},
{"learn":[0.05791110302],"iteration":967,"passed_time":18.2904163,"remaining_time":0.6046418612},
{"learn":[0.05788568873],"iteration":968,"passed_time":18.30641702,"remaining_time":0.5856542081},
{"learn":[0.05786766681],"iteration":969,"passed_time":18.32137612,"remaining_time":0.5666404984},
{"learn":[0.05784117009],"iteration":970,"passed_time":18.3358111,"remaining_time":0.5476194872},
{"learn":[0.05783441547],"iteration":971,"passed_time":18.35477034,"remaining_time":0.5287382403},
{"learn":[0.05780510489],"iteration":972,"passed_time":18.37449507,"remaining_time":0.509878075},
{"learn":[0.0577880574],"iteration":973,"passed_time":18.38917997,"remaining_time":0.4908816008},
{"learn":[0.05777635075],"iteration":974,"passed_time":18.40162016,"remaining_time":0.4718364143},
{"learn":[0.05777174828],"iteration":975,"passed_time":18.41591641,"remaining_time":0.4528504035},
{"learn":[0.05775596018],"iteration":976,"passed_time":18.43126048,"remaining_time":0.4338986602},
{"learn":[0.05774276905],"iteration":977,"passed_time":18.44730541,"remaining_time":0.4149700604},
{"learn":[0.05772122748],"iteration":978,"passed_time":18.46366925,"remaining_time":0.3960541922},
{"learn":[0.05768838869],"iteration":979,"passed_time":18.48435515,"remaining_time":0.3772317378},
{"learn":[0.05766552929],"iteration":980,"passed_time":18.51204121,"remaining_time":0.3585410632},
{"learn":[0.05765128612],"iteration":981,"passed_time":18.5349924,"remaining_time":0.3397452782},
{"learn":[0.05762109408],"iteration":982,"passed_time":18.57984657,"remaining_time":0.3213198287},
{"learn":[0.05760216471],"iteration":983,"passed_time":18.61279636,"remaining_time":0.3026470953},
{"learn":[0.0575875713],"iteration":984,"passed_time":18.63264286,"remaining_time":0.2837458303},
{"learn":[0.05758617235],"iteration":985,"passed_time":18.6525068,"remaining_time":0.2648428957},
{"learn":[0.05758058729],"iteration":986,"passed_time":18.6674901,"remaining_time":0.2458737298},
{"learn":[0.05754910153],"iteration":987,"passed_time":18.68469033,"remaining_time":0.2269395587},
{"learn":[0.05751774475],"iteration":988,"passed_time":18.69997255,"remaining_time":0.2079875612},
{"learn":[0.0574953367],"iteration":989,"passed_time":18.71414291,"remaining_time":0.1890317466},
{"learn":[0.05748349011],"iteration":990,"passed_time":18.72973251,"remaining_time":0.1700984789},
{"learn":[0.0574609976],"iteration":991,"passed_time":18.74985593,"remaining_time":0.1512085156},
{"learn":[0.0574531166],"iteration":992,"passed_time":18.765609,"remaining_time":0.1322852598},
{"learn":[0.05743401467],"iteration":993,"passed_time":18.78188409,"remaining_time":0.1133715337},
{"learn":[0.05740750166],"iteration":994,"passed_time":18.79905429,"remaining_time":0.09446760952},
{"learn":[0.05739034604],"iteration":995,"passed_time":18.81564459,"remaining_time":0.07556483771},
{"learn":[0.05736197857],"iteration":996,"passed_time":18.83072499,"remaining_time":0.05666216145},
{"learn":[0.05733408447],"iteration":997,"passed_time":18.8464242,"remaining_time":0.03776838516},
{"learn":[0.05731313784],"iteration":998,"passed_time":18.86286088,"remaining_time":0.01888174262},
{"learn":[0.05730840651],"iteration":999,"passed_time":18.8787854,"remaining_time":0}
]}